[
  {
    "id": "1730168997597",
    "title": "Halloween",
    "description": "__% off Halloween-themed items, last-minute offer.",
    "start": "2024-10-31",
    "end": "2024-10-31",
    "type": "SMS",
    "url": "",
    "color": "#564be6",
    "broadcastUrl": "https://www.emotiveapp.co/broadcast?&title=Halloween&message=~%23%7CBRAND%7C%23~%3A%20Boo!%20It's%20time%20to%20treat%20yourself%20to%20~%23%7C__%7C%23~%25%20off%20all%20Halloween%20faves.%20Don't%20ghost%20this%20deal%20%E2%80%93%20it's%20vanishing%20faster%20than%20a%20vampire%20at%20sunrise!%0A%0A%20~%23%7CLINK%7C%23~&utm_medium=guide"
  },
  {
    "id": "1730169075722",
    "title": "Early Access Starts Now",
    "description": "Build anticipation and excitement for the Early Access period, giving customers a sense of exclusivity.",
    "start": "2024-11-06",
    "end": "",
    "type": "SMS",
    "url": "",
    "color": "#564be6",
    "broadcastUrl": "https://www.emotiveapp.co/broadcast?&title=BFCM%20Early%20Access%204&message=~%23%7CBRAND%7C%23~%3A%20Psst...%20VIPs%2C%20we%20see%20you!%20%3Ashopping_bags%3A%20Start%20your%20Black%20Friday%20shopping%20spree%20early%20with%20an%20exclusive%20~%23%7C__%7C%23~%25%20off.%20Your%20favorites%20won't%20wait%20%E2%80%93%20why%20should%20you%3F%0A%0A%20~%23%7CLINK%7C%23~&utm_medium=guide"
  },
  {
    "id": "1730169144970",
    "title": "Early Access in Full Swing",
    "description": "Remind subscribers that Early Access deals are live and create urgency with time-sensitive language.",
    "start": "2024-11-08",
    "end": "",
    "type": "SMS",
    "url": "",
    "color": "#564be6",
    "broadcastUrl": "https://www.emotiveapp.co/broadcast?&title=BFCM%20Early%20Access&message=~%23%7CBRAND%7C%23~%3A%20Hey%20%3C%20first_name%3E%2C%20early%20access%20is%20unlocked!%20Beat%20the%20Black%20Friday%20rush%20and%20claim%20your%20__%25%20OFF%20sitewide%20today.%20%0A%0AShop%20before%20it's%20gone%3A%20~%23%7CLINK%7C%23~&imageUrl=https%3A%2F%2Fimages.ctfassets.net%2Fdhi2t25jmryf%2F6kdFJuLeN424g9RAr6Z5Up%2F19c73f5fb2714f3075a37edc81e21b31%2Fblackfriday-earlyaccess.gif&utm_medium=guide"
  },
  {
    "id": "1730169179794",
    "title": "Early Access at Its Peak",
    "description": "Keep the momentum going by emphasizing scarcity and limited-time availability.",
    "start": "2024-11-11",
    "end": "",
    "type": "SMS",
    "url": "",
    "color": "#564be6",
    "broadcastUrl": "https://www.emotiveapp.co/broadcast?&title=BFCM%20Early%20Access%202&message=~%23%7CBRAND%7C%23~%3A%20Hey%20%3C%20first_name%3E%2C%20you%E2%80%99re%20first%20in%20line!%20Get%20ahead%20of%20Black%20Friday%20with%20exclusive%20early%20access%20and%20__%25%20OFF%20sitewide.%20%0A%0ADon%E2%80%99t%20wait%2C%20start%20shopping%20now%3A%0A%0A%20~%23%7CLINK%7C%23~&imageUrl=https%3A%2F%2Fimages.ctfassets.net%2Fdhi2t25jmryf%2F4OhfJ5dWL5epyfeYlsvhdY%2F58d6cfa46af74493bb6ac068ad705d23%2Fbf-ea.gif&utm_medium=guide"
  },
  {
    "id": "1730169217230",
    "title": "Early Access Ending Soon",
    "description": "Use FOMO (fear of missing out) to encourage customers to act before Early Access ends.",
    "start": "2024-11-13",
    "end": "",
    "type": "SMS",
    "url": "",
    "color": "#564be6",
    "broadcastUrl": "https://www.emotiveapp.co/broadcast?&title=BFCM%20Early%20Access%203&message=~%23%7CBRAND%7C%23~%3A%20Unlock%20Early%20Access!%20Get%20first%20dibs%20on%20Black%20Friday%20deals%20with%20%20~%23%7C__%7C%23~%25%20off%20%E2%80%93%20because%20why%20wait%20for%20the%20crowd%20when%20you%20can%20shop%20like%20a%20VIP%20today%3F%0A%0A%20~%23%7CLINK%7C%23~&imageUrl=https%3A%2F%2Fimages.ctfassets.net%2Fdhi2t25jmryf%2F7Dza5rHaGz6VCETPgFL7m8%2F921297bbac9e3e73930c7022d0a11fa5%2Fbf-earlyhere.gif&utm_medium=guide"
  },
  {
    "id": "1730169250420",
    "title": "BFCM Early Access Almost Over",
    "description": "Emphasize the urgency of shopping before Early Access closes and the main Black Friday event begins.",
    "start": "2024-11-17",
    "end": "",
    "type": "SMS",
    "url": "",
    "color": "#564be6",
    "broadcastUrl": "https://www.emotiveapp.co/broadcast?&title=Almost%20Over%201&message=~%23%7CBRAND%7C%23~%3A%20Final%20lap!%20Early%20Access%20is%20almost%20over%E2%80%94lock%20in%20your%20exclusive%20Black%20Friday%20deals%20now!%0A%0A~%23%7CLINK%7C%23~&utm_medium=guide"
  },
  {
    "id": "1730169317504",
    "title": "Early Access Ends Soon",
    "description": "This is the last opportunity to take advantage of Early Access before the main Black Friday sale begins.",
    "start": "2024-11-22",
    "end": "",
    "type": "SMS",
    "url": "",
    "color": "#564be6",
    "broadcastUrl": "https://www.emotiveapp.co/broadcast?&title=BFCM%20Early%20Access%207&message=~%23%7CBRAND%7C%23~%3A%20Last%20call!%20Early%20Access%20deals%20vanish%20TONIGHT!%20Grab%20up%20to%20~%23%7C__%7C%23~%25%20off%20or%20snag%20our%20exclusive%20bundles%20before%20they%E2%80%99re%20history.%20Clock%E2%80%99s%20ticking!%20%E2%8F%B3%0A%0A%20~%23%7CLINK%7C%23~&utm_medium=guide"
  },
  {
    "id": "1730169370143",
    "title": "Thanksgiving Specials",
    "description": "Express appreciation for your customers while reminding them of ongoing or upcoming deals.",
    "start": "2024-11-28",
    "end": "",
    "type": "SMS",
    "url": "",
    "color": "#564be6",
    "broadcastUrl": "https://www.emotiveapp.co/broadcast?&title=BFCM%20Early%20Access%208&message=~%23%7CBRAND%7C%23~%3A%20%F0%9F%8D%82%20Grateful%20for%20YOU!%20As%20a%20token%20of%20thanks%2C%20enjoy%20~%23%7Coffer%7C%23~.%20Spend%20your%20holiday%20with%20us%20%E2%80%93%20treat%20yourself%20and%20your%20loved%20ones.%20%F0%9F%99%8C%0A%0A%20~%23%7CLINK%7C%23~&utm_medium=guide"
  },
  {
    "id": "1730169483743",
    "title": "Giving Tuesday",
    "description": "Use Giving Tuesday as an opportunity to promote self-care and encourage customers to prioritize themselves with exclusive deals.",
    "start": "2024-12-03",
    "end": "",
    "type": "SMS",
    "url": "",
    "color": "#564be6",
    "broadcastUrl": "https://www.emotiveapp.co/broadcast?&title=Giving%20Tuesday%201&message=~%23%7CBRAND%7C%23~%3A%20This%20Giving%20Tuesday%2C%20give%20yourself%20something%20special!%20%F0%9F%8E%81%20Exclusive%20deals%20are%20waiting%20for%20you.%0A%0A~%23%7CLINK%7C%23~&utm_medium=guide"
  },
  {
    "id": "1730169545798",
    "title": "Extended Savings Alert",
    "description": "Let customers know they still have time to take advantage of the Black Friday/Cyber Monday deals they may have missed.",
    "start": "2024-12-05",
    "end": "",
    "type": "SMS",
    "url": "",
    "color": "#564be6",
    "broadcastUrl": "https://www.emotiveapp.co/broadcast?&title=Black%20Friday%2FCyber%20Monday%20Extension%201&message=~%23%7CBRAND%7C%23~%3A%20Did%20you%20miss%20out%20on%20Black%20Friday%20%26%20Cyber%20Monday%3F%20We%E2%80%99ve%20got%20your%20back.%2048%20hours%20left%20to%20save%20BIG%20on%20what%E2%80%99s%20left!%20Don%E2%80%99t%20wait%2C%20shop%20now.%20~%23%7CLINK%7C%23~&utm_medium=guide"
  },
  {
    "id": "1730169587119",
    "title": "Countdown to Holiday Savings",
    "description": "Build excitement as the holidays approach, reminding shoppers to complete their gift buying before time runs out.",
    "start": "2024-12-08",
    "end": "",
    "type": "SMS",
    "url": "",
    "color": "#564be6",
    "broadcastUrl": "https://www.emotiveapp.co/broadcast?&title=Holiday%20Hustle%20Countdown%201&message=~%23%7CBRAND%7C%23~%3A%20Your%20holiday%20hustle%20starts%20NOW!%20Stock%20up%20on%20gifts%20with%20~%23%7C__%7C%23~%25%20off%20%E2%80%93%20perfect%20for%20everyone%20on%20your%20list.%20Hurry%2C%20holiday%20magic%20won%E2%80%99t%20last!%20~%23%7CLINK%7C%23~&utm_medium=guide"
  },
  {
    "id": "1730169622452",
    "title": "Last-Minute Stocking Stuffers",
    "description": "Target last-minute shoppers with small, thoughtful gift ideas that can still arrive in time for the holidays.",
    "start": "2024-12-10",
    "end": "",
    "type": "SMS",
    "url": "",
    "color": "#564be6",
    "broadcastUrl": "https://www.emotiveapp.co/broadcast?&title=Last-Minute%20Stocking%20Stuffers%201&message=~%23%7CBRAND%7C%23~%3A%20%F0%9F%A7%A6%20Still%20need%20stocking%20stuffers%3F%20We%E2%80%99ve%20got%20your%20back!%20Shop%20~%23%7C__%7C%23~%25%20off%20last-minute%20gems%20and%20get%20them%20just%20in%20time.%20Hurry%2C%20before%20the%20elves%20take%20them%20all!%20~%23%7CLINK%7C%23~%0A&utm_medium=guide"
  },
  {
    "id": "1730169717822",
    "title": "Holiday Gift Frenzy",
    "description": "Promote the excitement of finding all holiday gifts in one place with special deals for the season.",
    "start": "2024-12-12",
    "end": "",
    "type": "SMS",
    "url": "",
    "color": "#564be6",
    "broadcastUrl": "https://www.emotiveapp.co/broadcast?&title=Gift%20Frenzy%201&message=~%23%7CBRAND%7C%23~%3A%20The%20more%20you%20shop%2C%20the%20more%20we%20gift!%20For%20every%20order%20today%2C%20we%E2%80%99re%20giving%20YOU%20something%20extra.%20Don't%20miss%20out%20on%20the%20ultimate%20gift%20frenzy!%20~%23%7CLINK%7C%23~&imageUrl=https%3A%2F%2Fimages.ctfassets.net%2Fdhi2t25jmryf%2F1q3GIrpX2rJePWY0IMK4Y1%2Fd15748092653a7b4bdb9c7007ac4a244%2Ffd2c1a96b654e220d09525f006482477.gif&utm_medium=guide"
  },
  {
    "id": "1730169745146",
    "title": "Season of Surprises",
    "description": "Focus on delivering unexpected value to your customers with special surprise deals.",
    "start": "2024-12-14",
    "end": "",
    "type": "SMS",
    "url": "",
    "color": "#564be6",
    "broadcastUrl": "https://www.emotiveapp.co/broadcast?&title=Season%20of%20Surprises%201&message=~%23%7CBRAND%7C%23~%3A%20%F0%9F%8E%85%20Ready%20for%20a%20surprise%3F%20We%E2%80%99ve%20got%20mystery%20deals%20for%20YOU!%20Unwrap%20up%20to%20~%23%7C__%7C%23~%25%20off%20or%20a%20surprise%20gift%20with%20every%20order.%20What%20will%20you%20get%3F%20~%23%7CLINK%7C%23~&imageUrl=https%3A%2F%2Fimages.ctfassets.net%2Fdhi2t25jmryf%2FoLymUiMgFtW9RJFCKR4dK%2Fdb0020eea718f4a9c7379616cc2417f8%2Fcats.gif&utm_medium=guide"
  },
  {
    "id": "1730906862949",
    "title": "Task: Set Up Automated Flows for BFCM",
    "description": "Ensure automated abandoned emails and SMS are ready to trigger during BFCM. Tailor messaging to include urgency and highlight limited-time deals.",
    "start": "2024-11-07",
    "end": "2024-11-07",
    "type": "Task",
    "url": "",
    "color": "#808080",
    "broadcastUrl": ""
  },
  {
    "id": "1730906938721",
    "title": "Task: Finalize Inventory Checks",
    "description": "Stock Assessment: Make sure high-demand products are well-stocked to avoid running out mid-event.\n\nLow Stock Alerts: Set up alerts for products nearing depletion to adjust promotions accordingly.",
    "start": "2024-11-01",
    "end": "2024-11-01",
    "type": "Task",
    "url": "",
    "color": "#808080",
    "broadcastUrl": ""
  },
  {
    "id": "1730907086795",
    "title": "Task: Segment Your Audience",
    "description": "Create Segments: Divide your SMS list into key groups like VIPs, past purchasers, first-time buyers, and high-intent customers.\n\nTargeted Messaging: Craft specific messages for each segment to personalize the experience and boost conversions.",
    "start": "2024-11-05",
    "end": "2024-11-05",
    "type": "Task",
    "url": "",
    "color": "#808080",
    "broadcastUrl": ""
  },
  {
    "id": "1730907269075",
    "title": "Task: Create a BFCM SMS Calendar",
    "description": "Plan out the exact days and times you’ll send messages. Include reminders for early access, ongoing deals, low-stock warnings, and last-chance offers",
    "start": "2024-11-01",
    "end": "2024-11-01",
    "type": "Task",
    "url": "",
    "color": "#808080",
    "broadcastUrl": ""
  },
  {
    "id": "1730907308254",
    "title": "Task: Promote SMS Sign-Up on Other Channels",
    "description": "Use email, social media, and your website to encourage customers to join your SMS list before BFCM. Highlight exclusive deals and perks available only through SMS.",
    "start": "2024-11-12",
    "end": "2024-11-12",
    "type": "Task",
    "url": "",
    "color": "#808080",
    "broadcastUrl": ""
  },
  {
    "id": "1730907372346",
    "title": "Task: Use SMS to Upsell and Cross-Sell Post-Purchase",
    "description": "Send personalized product recommendations immediately after a customer receives their purchase.\n\nExample: “Thanks for your order! Complete your look with [Related Product] at 10% off. ",
    "start": "2024-11-15",
    "end": "",
    "type": "Task",
    "url": "",
    "color": "#808080",
    "broadcastUrl": ""
  },
  {
    "id": "1730909131599",
    "title": "Task: Send Multiple SMS Messages During Black Friday",
    "description": "Sending more than one message on Black Friday ensures your deals stand out amidst the overwhelming competition. With customers shopping at different times, multiple reminders help create urgency, target various time zones, and capture both early and last-minute buyers. This strategy keeps your brand top-of-mind and maximizes engagement throughout the day.\n\nExamples:\nMorning (8 AM)\nAfternoon (12 PM)\nEvening (6 PM)",
    "start": "2024-11-29",
    "end": "",
    "type": "Task",
    "url": "",
    "color": "#808080",
    "broadcastUrl": ""
  },
  {
    "id": "1730909183499",
    "title": "Black Friday Kickoff",
    "description": "Launch the main Black Friday sale with a sense of excitement and urgency.",
    "start": "2024-11-29",
    "end": "",
    "type": "SMS",
    "url": "",
    "color": "#564be6",
    "broadcastUrl": "https://www.emotiveapp.co/broadcast?&title=Black%20Friday%20Main%20Event%201&message=~%23%7CBRAND%7C%23~%3A%20%F0%9F%94%A5%20This%20is%20IT.%20Black%20Friday%E2%80%99s%20biggest%20deals%20are%20LIVE!%20Save%20up%20to%20~%23%7Coffer%7C%23~%25%20on%20~%23%7Cspecific%20product%7C%23~.%20Don%E2%80%99t%20blink%20and%20miss%20our%20limited-time%20drops.%0A%0AShop%20fast!%20~%23%7CLINK%7C%23~&utm_medium=guide"
  },
  {
    "id": "1730909216993",
    "title": "Black Friday Kickoff 2",
    "description": "Launch the main Black Friday sale with a sense of excitement and urgency.",
    "start": "2024-11-29",
    "end": "",
    "type": "SMS",
    "url": "",
    "color": "#564be6",
    "broadcastUrl": "https://www.emotiveapp.co/broadcast?&title=Black%20Friday%20Kickoff%202&message=~%23%7CBRAND%7C%23~%3A%20Black%20Friday%20starts%20now!%20%F0%9F%8E%89%20Unbeatable%20deals%20you%E2%80%99ve%20been%20waiting%20for.%20Shop%20fast!%0A%0A~%23%7CLINK%7C%23~&utm_medium=guide"
  },
  {
    "id": "1730909279645",
    "title": "Black Friday Kickoff 3",
    "description": "Launch the main Black Friday sale with a sense of excitement and urgency.",
    "start": "2024-11-29",
    "end": "",
    "type": "SMS",
    "url": "",
    "color": "#564be6",
    "broadcastUrl": "https://www.emotiveapp.co/broadcast?&title=Black%20Friday%20Kickoff%203&message=~%23%7CBRAND%7C%23~%3A%20Black%20Friday%20is%20ON!%20%F0%9F%94%A5%20Deals%20so%20good%2C%20they%20won%E2%80%99t%20last%20long.%20Don%E2%80%99t%20wait%E2%80%94shop%20now!%0A%0A~%23%7CLINK%7C%23~&utm_medium=guide"
  },
  {
    "id": "1730909409578",
    "title": "Send Multiple SMS Messages During Cyber Monday",
    "description": "Cyber Monday is one of the most competitive online shopping days, and sending multiple SMS messages ensures your offers stay visible amid the digital noise. With customers browsing throughout the day, staggered messages can target different shopping behaviors—early birds, midday deal seekers, and last-minute buyers. This strategy maximizes engagement, boosts sales, and helps capture every possible conversion opportunity.",
    "start": "2024-12-02",
    "end": "",
    "type": "Task",
    "url": "",
    "color": "#808080",
    "broadcastUrl": ""
  },
  {
    "id": "1730909447153",
    "title": "Cyber Monday Has Arrived",
    "description": "Highlight the urgency and exclusivity of the biggest online shopping day. Encourage immediate action.",
    "start": "2024-12-02",
    "end": "",
    "type": "SMS",
    "url": "",
    "color": "#564be6",
    "broadcastUrl": "https://www.emotiveapp.co/broadcast?&title=Cyber%20Monday%20Main%20Event%201&message=~%23%7CBRAND%7C%23~%3A%20%F0%9F%92%BB%20Cyber%20Monday%20secret%3A%20Exclusive%20online%20deals%20you%20won%E2%80%99t%20find%20ANYWHERE%20else.%20Save%20big%20on%20~%23%7Cproduct%20or%20service%7C%23~.%20Only%20for%20today%2C%20so%20don%E2%80%99t%20sleep%20on%20this!%20~%23%7CLINK%7C%23~&utm_medium=guide"
  },
  {
    "id": "1730909500843",
    "title": "Cyber Monday Has Arrived 2",
    "description": "Highlight the urgency and exclusivity of the biggest online shopping day. Encourage immediate action.",
    "start": "2024-12-02",
    "end": "",
    "type": "SMS",
    "url": "",
    "color": "#564be6",
    "broadcastUrl": "https://www.emotiveapp.co/broadcast?&title=Cyber%20Monday%20Has%20Arrived%202&message=~%23%7CBRAND%7C%23~%3A%20Cyber%20Monday%20savings%20start%20now!%20%F0%9F%92%BB%20Don%E2%80%99t%20miss%20your%20chance%20to%20score%20exclusive%20online%20deals.%0A%0A~%23%7CLINK%7C%23~&utm_medium=guide"
  },
  {
    "id": "1730909523725",
    "title": "Cyber Monday Has Arrived 3",
    "description": "Highlight the urgency and exclusivity of the biggest online shopping day. Encourage immediate action.",
    "start": "2024-12-02",
    "end": "",
    "type": "SMS",
    "url": "",
    "color": "#564be6",
    "broadcastUrl": "https://www.emotiveapp.co/broadcast?&title=Cyber%20Monday%20Has%20Arrived%202%20(1)&message=~%23%7CBRAND%7C%23~%3A%20%F0%9F%9A%A8%20Cyber%20Monday%20is%20here!%20Shop%20our%20best%20deals%20of%20the%20season%20before%20they%E2%80%99re%20gone.%20Deals%20end%20at%20midnight!%0A%0A~%23%7CLINK%7C%23~&utm_medium=guide"
  },
  {
    "id": "1734626423604",
    "title": "Last Night of Hanukkah",
    "description": "Cheers to the last night of Hanukkah! Make sure your subscribers know you're thinking about them with a message of gratitude and luck for a lovely rest of the year.",
    "start": "2024-12-15",
    "end": "2024-12-15",
    "type": "SMS",
    "url": "",
    "color": "#4c11ee",
    "broadcastUrl": "https://www.emotiveapp.co/broadcast?&title=Last%20Night%20of%20Hanukkah&message=~%23%7CBRAND%7C%23~%3A%20Light%20up%20the%20last%20night%20of%20Hanukkah%20with%20our%20latest%20this%20Hanukkah.%20Celebrate%20the%20first%20night%20with%20special%20deals%20just%20for%20you.%20Illuminate%20your%20holiday!%20~%23%7CLINK%7C%23~&imageUrl=https%3A%2F%2Fimages.ctfassets.net%2Fdhi2t25jmryf%2F1zYjR7TyjWnQ4mhsnChBbc%2Fe914477efffc101f50b7a6dfdca200b7%2FGIF_-15_Hanukkah.gif&utm_medium=guide"
  },
  {
    "id": "1734626692923",
    "title": "Super Saturday",
    "description": "We're just ONE week away from the holiday weekend. Offer a flash sale to entice your customers to get those last minute purchases made in time for the big day.",
    "start": "2024-12-21",
    "end": "2024-12-21",
    "type": "SMS",
    "url": "",
    "color": "#4c11ee",
    "broadcastUrl": "https://www.emotiveapp.co/broadcast?&title=Super%20Saturday&message=~%23%7CBRAND%7C%23~%3A%20%F0%9F%8E%89%20Super%20Saturday%20Alert!%20%F0%9F%8E%89%20Get%20your%20last-minute%20gifts%20with%20fantastic%20deals%20only%20available%20today!%20Hurry%2C%20shop%20now%3A%20~%23%7CLINK%7C%23~&imageUrl=https%3A%2F%2Fimages.ctfassets.net%2Fdhi2t25jmryf%2F5Ds5WIQBqUH4lACdK5ZQvR%2F51945ff84b967f1cf45c57779135535e%2FGIF_-17_Super_Saturday.gif&utm_medium=guide"
  },
  {
    "id": "1734626837238",
    "title": "Christmas Eve",
    "description": "Got a deal to share with the subscribers who waited to shop until the very last minute? Share it on Christmas Eve!",
    "start": "2024-12-24",
    "end": "2024-12-24",
    "type": "SMS",
    "url": "",
    "color": "#4c11ee",
    "broadcastUrl": "https://www.emotiveapp.co/broadcast?&title=Christmas%20Eve&message=~%23%7CBRAND%7C%23~%3A%20Hear%20the%20sleigh%20bells%3F%20It's%20not%20too%20late%20for%20last-minute%20miracles%20with%20BRAND%20this%20Christmas%20Eve!%20%F0%9F%8E%85%20Dash%20through%20our%20holiday%20deals%3A%20~%23%7CLINK%7C%23~&imageUrl=https%3A%2F%2Fimages.ctfassets.net%2Fdhi2t25jmryf%2F5JFDuB4Y8MYe7SXARXqtgG%2F211f29ecaf875e80c46a190889489ac8%2FGIF_-9_Christmas_Eve.gif&utm_medium=guide"
  },
  {
    "id": "1734627012411",
    "title": "Christmas Day",
    "description": "Wish your subscribers a wonderful Christmas Day filled with friends and family by sending out a heartfelt message — no promo necessary. ",
    "start": "2024-12-25",
    "end": "2024-12-25",
    "type": "SMS",
    "url": "",
    "color": "#4c11ee",
    "broadcastUrl": "https://www.emotiveapp.co/broadcast?&title=Christmas%20Day&message=Wishing%20you%20a%20cozy%20Christmas%20Day%20from%20all%20of%20us%20at%20~%23%7CBRAND%7C%23~!%20%F0%9F%8E%81%20Snuggle%20up%20with%20our%20holiday%20specials%20and%20let%20the%20spirit%20move%20you.%20Shop%20warmth%20%26%20wonder%3A%20~%23%7CLINK%7C%23~&imageUrl=https%3A%2F%2Fimages.ctfassets.net%2Fdhi2t25jmryf%2F1d59viqultQxD15gkDZ4ZQ%2Ffd430114792bcd8c26e1cc0585f615c7%2FGIF_-10_Christmas_Day.gif&utm_medium=guide"
  },
  {
    "id": "1734627173385",
    "title": "Christmas Sale - Announcement",
    "description": "Let your subscribers know you're sending them a gift for the holidays: a 1-day flash sale or a super special deal on products! ",
    "start": "2024-12-25",
    "end": "2024-12-25",
    "type": "SMS",
    "url": "",
    "color": "#4c11ee",
    "broadcastUrl": "https://www.emotiveapp.co/broadcast?&title=Christmas%20Sale%20-%20Announcement&message=Jingle%20all%20the%20way%20to%20savings!%20The%20~%23%7CBRAND%7C%23~!%20Christmas%20Sale%20is%20here%20-%20exclusive%20deals%20just%20for%20you.%F0%9F%8E%84%20Dive%20into%20the%20festive%20cheer%20and%20save%20big%3A%20~%23%7CLINK%7C%23~%20Offer%20valid%20till%20~%23%7CDATE%7C%23~&imageUrl=https%3A%2F%2Fimages.ctfassets.net%2Fdhi2t25jmryf%2F7IRrT3iQzEACMS8Q9N5VEh%2F189d91a9f76aace0703794895782d6e0%2FGIF_-3_Christmas_Sale_-_Announcement.gif&utm_medium=guide"
  },
  {
    "id": "1734627685159",
    "title": "Christmas Sale - Reminder",
    "description": "Remind your subscribers to take a break from the holiday festivities and send some cheer their way with your Christmas sale! ",
    "start": "2024-12-25",
    "end": "2024-12-25",
    "type": "SMS",
    "url": "",
    "color": "#4c11ee",
    "broadcastUrl": "https://www.emotiveapp.co/broadcast?&title=Christmas%20Sale%20-%20Reminder&message=~%23%7CBRAND%7C%23~%3A%20Wish%20upon%20a%20star%20because%20Christmas%20wishes%20have%20been%20coming%20true%20with%20our%20sale!%20%F0%9F%8C%A0%20Up%20to%20~%23%7CDISCOUNT%7C%23~%25%20off%20starts%20now.%20Don't%20wait%20for%20Santa%2C%20grab%20your%20deals%3A%20~%23%7CLINK%7C%23~%20Sale%20till%20~%23%7CDATE%7C%23~&imageUrl=https%3A%2F%2Fimages.ctfassets.net%2Fdhi2t25jmryf%2F7HjtWZPjOzjmj1Oht6KHI8%2F5847fee0c41848b75b42ba82ec22af56%2FGIF_-4_Christmas_Sale_-_Reminder.gif&utm_medium=guide"
  },
  {
    "id": "1734628086405",
    "title": "Christmas Sale - Last Chance",
    "description": "Want to remind your subscribers of your deals before the day is over? Send them a very last chance message! Pro tip: send it to a segment of those who have clicked on the previous messages. \n",
    "start": "2024-12-25",
    "end": "2024-12-25",
    "type": "SMS",
    "url": "",
    "color": "#4c11ee",
    "broadcastUrl": "https://www.emotiveapp.co/broadcast?&title=Christmas%20Sale%20-%20Last%20Chance&message=~%23%7CBRAND%7C%23~%3A%20Final%20hours!%20Don%E2%80%99t%20miss%20out%20on%20our%20festive%20deals.%20Up%20to%20~%23%7CDISCOUNT%7C%23~%25%20off%20ends%20at%20midnight.%20Grab%20your%20last-minute%20gifts%20now%3A%20~%23%7CLINK%7C%23~%20&imageUrl=https%3A%2F%2Fimages.ctfassets.net%2Fdhi2t25jmryf%2F5A1XgMVqlW3cBQqVFkeYvm%2F37d2b6df65c5aaad7416649db5a56f59%2FGIF_-5_Christmas_Sale_-_Last_Chance.gif&utm_medium=guide"
  },
  {
    "id": "1734628223084",
    "title": "Boxing Day",
    "description": "Christmas may be over, but the sales sure aren't! Offer your subscribers a flash sale on Boxing Day to clear out extra inventory or to make room for new arrivals for 2025.",
    "start": "2024-12-26",
    "end": "2024-12-26",
    "type": "SMS",
    "url": "",
    "color": "#4c11ee",
    "broadcastUrl": "https://www.emotiveapp.co/broadcast?&title=Boxing%20Day&message=~%23%7CBRAND%7C%23~%3A%20%F0%9F%93%A6%20Box%20up%20the%20savings!%20Our%20Boxing%20Day%20Sale%20is%20a%20knockout%20-%20up%20to%20~%23%7CDISCOUNT%7C%23~%25%20off%20everything.%20Shop%20till%20you%20drop!%20%20~%23%7CLINK%7C%23~%20&imageUrl=https%3A%2F%2Fimages.ctfassets.net%2Fdhi2t25jmryf%2F6s7vMmJzDYxsuHi1mbOfxX%2F9583aca065afb2751154d5500ee1885c%2FGIF_-16_Boxing_Day.gif&utm_medium=guide"
  },
  {
    "id": "1734628346490",
    "title": "Kwanzaa Begins",
    "description": "Christmas and Hanukkah may be over, but Kwanzaa is just getting started! Be sure to share a message of celebration with your subscribers.",
    "start": "2024-12-26",
    "end": "2024-12-26",
    "type": "SMS",
    "url": "",
    "color": "#4c11ee",
    "broadcastUrl": "https://www.emotiveapp.co/broadcast?&title=Kwanzaa%20Begins&message=~%23%7CBRAND%7C%23~%3A%20Happy%20Kwanzaa!%20%F0%9F%95%AF%EF%B8%8F%20Let's%20celebrate%20unity%2C%20self-determination%2C%20and%20collective%20work%20and%20responsibility.%20Begin%20this%20vibrant%20cultural%20celebration%20with%20us.%20Enjoy%20special%20offers%3A%20~%23%7CLINK%7C%23~%20&imageUrl=https%3A%2F%2Fimages.ctfassets.net%2Fdhi2t25jmryf%2F2rq2AvSFItIK6WTFp6GmsZ%2F4f848f55cb61be34f994ec6192036010%2FGIF_-11_Kwanzaa.gif&utm_medium=guide"
  },
  {
    "id": "1734628627648",
    "title": "Winter Solstice",
    "description": "Winter is here! Spotlight your cold-weather best-sellers or offer a sitewide sale for the big day.",
    "start": "2024-12-21",
    "end": "2024-12-21",
    "type": "SMS",
    "url": "",
    "color": "#4c11ee",
    "broadcastUrl": "https://www.emotiveapp.co/broadcast?&title=Winter%20Solstice&message=~%23%7CBRAND%7C%23~%3A%20The%20shortest%20day%2C%20the%20sweetest%20deal!%20Celebrate%20the%20season%20with%20~%23%7CDISCOUNT%7C%23~%20%25%20off%20PRODUCT.%20Our%20Winter%20Solstice%20Sale%20ends%20~%23%7CDATE%7C%23~%2C%20so%20hurry%E2%80%94shop%20now%3A%20~%23%7CLINK%7C%23~%20&imageUrl=https%3A%2F%2Fimages.ctfassets.net%2Fdhi2t25jmryf%2F3w1rDAtLvcJkUobSdLKzEw%2Fb1b323f33e32b21d06368c2c1b746f96%2FGIF_-18_First_Day_of_Winter.gif&utm_medium=guide"
  },
  {
    "id": "1734629345745",
    "title": "National Fruitcake Day",
    "description": "Forgot a gift? No problem! Fruitcake to the rescue! Celebrate National Fruitcake Day and make your holiday gatherings extra special!",
    "start": "2024-12-27",
    "end": "2024-12-27",
    "type": "SMS",
    "url": "",
    "color": "#4c11ee",
    "broadcastUrl": "https://www.emotiveapp.co/broadcast?&title=National%20Fruitcake%20Day&message=~%23%7CBRAND%7C%23~%3A%20Did%20you%20know%20fruitcake%20is%20the%20OG%20of%20holiday%20treats%3F%20%F0%9F%A5%AECelebrate%20National%20Fruitcake%20Day%20with%20~%23%7CDISCOUNT%7C%23~%25%20off%20and%20sweeten%20up%20your%20day%20with%20a%20slice%20of%20history!%20Shop%20here%3A%20~%23%7CLINK%7C%23~%20&imageUrl=https%3A%2F%2Fimages.ctfassets.net%2Fdhi2t25jmryf%2F5Q0b8gQewmkS0BbhWVjBxq%2F5ed85a5590a4447c99b527c8901b4381%2FGIF_-1_Holiday_Gifting.gif&utm_medium=guide"
  },
  {
    "id": "1734629534536",
    "title": "Holiday Shipping - Last Call",
    "description": "Time is running out! Make sure your subscribers take advantage of your shipping offers before it's too late.",
    "start": "2024-12-19",
    "end": "2024-12-19",
    "type": "SMS",
    "url": "",
    "color": "#4f11ee",
    "broadcastUrl": "https://www.emotiveapp.co/broadcast?&title=Holiday%20Shipping%20-%20Last%20Call&message=~%23%7CBRAND%7C%23~%3A%20Last%20call%20for%20for%20holiday%20delivery%20on%20standard%20shipping!%20Don%E2%80%99t%20wait%20til%20it%E2%80%99s%20too%20late%2C%20shop%20TODAY%3A%20~%23%7CLINK%7C%23~%20&imageUrl=https%3A%2F%2Fimages.ctfassets.net%2Fdhi2t25jmryf%2F7l7wkMJqwmxtK0kmS0nZhp%2F68db4f14072b536d917f621a2a0e0d24%2FShipping_Deadline_Last_Call.gif&utm_medium=guide"
  },
  {
    "id": "1734629648220",
    "title": "Holiday Shipping - Second Reminder",
    "description": "Sometimes subscribers need a push to take advantage of your deals! Pro tip: include the date of when a product needs to be ordered for guaranteed delivery by the 24th.",
    "start": "2024-12-18",
    "end": "2024-12-18",
    "type": "SMS",
    "url": "",
    "color": "#4f11ee",
    "broadcastUrl": "https://www.emotiveapp.co/broadcast?&title=Holiday%20Shipping%20-%20Second%20Reminder&message=~%23%7CBRAND%7C%23~%3A%20Hey%20~%23%7CNAME%7C%23~!%20Order%20by%20~%23%7CDATE%7C%23~%20for%20guaranteed%20delivery%20by%20the%20holidays.%20Sleigh's%20loading%20up%2C%20hurry!%20~%23%7CLINK%7C%23~%20&imageUrl=https%3A%2F%2Fimages.ctfassets.net%2Fdhi2t25jmryf%2F5b9cIxkfywJVUjZ96pfMC3%2Fa85ce5f1f996f8d032c8e379874c0718%2FShipping_Deadline.gif&utm_medium=guide"
  },
  {
    "id": "1734629751306",
    "title": "Holiday Shipping - First Reminder",
    "description": "If you're offering free shipping or a special rate for more than one day, try sending a reminder to your subscribers who clicked on the link of the first announcement, but haven't made a purchase yet.",
    "start": "2024-12-17",
    "end": "2024-12-17",
    "type": "SMS",
    "url": "",
    "color": "#4f11ee",
    "broadcastUrl": "https://www.emotiveapp.co/broadcast?&title=Holiday%20Shipping%20-%20First%20Reminder&message=~%23%7CBRAND%7C%23~%3A%20No%20time%20to%20waste%2C%20~%23%7CNAME%7C%23~!%20Order%20today%20by%20~%23%7CDATE%7C%23~%20for%20assured%20delivery.%20Start%20shopping%3A%20%20~%23%7CLINK%7C%23~%20&imageUrl=https%3A%2F%2Fimages.ctfassets.net%2Fdhi2t25jmryf%2F2iHSDuVjEAGluk4vNDNq7m%2Fc2f8f034e8883fd7f9dcbcedc5aca183%2FShipping-Deadline-Reminder.gif&utm_medium=guide"
  },
  {
    "id": "1734630031539",
    "title": "Rewards Program",
    "description": "Turn holiday shoppers into loyal customers. Highlight rewards benefits during peak shopping season to boost program signups.",
    "start": "2024-12-20",
    "end": "2024-12-20",
    "type": "SMS",
    "url": "",
    "color": "#4f11ee",
    "broadcastUrl": "https://www.emotiveapp.co/broadcast?&title=Rewards%20Program&message=~%23%7CBRAND%7C%23~%3A%20Shop%20%26%20earn%20this%20holiday!%20Join%20our%20rewards%20program%20for%20instant%20perks%20%2B%20bonus%20points%20on%20every%20purchase%3A%20~%23%7CLINK%7C%23~%20&imageUrl=https%3A%2F%2Fimages.ctfassets.net%2Fdhi2t25jmryf%2F2VDIdTKm36V2x2slV7Fi4B%2Fb248b231a7ae8287a391ff445396f848%2FRewards_Program.gif&utm_medium=guide"
  },
  {
    "id": "1734630232795",
    "title": "Holiday Giving",
    "description": "Show subscribers how their holiday shopping creates real impact. Share your brand's charitable partnerships and give customers a chance to be part of something meaningful.",
    "start": "2024-12-22",
    "end": "2024-12-22",
    "type": "SMS",
    "url": "",
    "color": "#4f11ee",
    "broadcastUrl": "https://www.emotiveapp.co/broadcast?&title=Holiday%20Giving&message=~%23%7CBRAND%7C%23~%3A%20This%20season%2C%20your%20shopping%20makes%20a%20difference.%20~%23%7CDISCOUNT%7C%23~%25%20goes%20to%20~%23%7CORGANIZATION%7C%23~%20through%20~%23%7CDATE%7C%23~.%20Join%20us%20in%20giving%20back%3A%20~%23%7CLINK%7C%23~%20&imageUrl=https%3A%2F%2Fimages.ctfassets.net%2Fdhi2t25jmryf%2F1fSnj3mTJBz5q3c0ZgDH3t%2Fc9391ceaf6657b93146ee8da58af0af8%2FGIF_-4_Holiday_Giving.gif&utm_medium=guide"
  },
  {
    "id": "1734630356585",
    "title": "Holiday Gift Cards",
    "description": "Whether you're running a sale or not, suggest Gift Cards for the indecisive shoppers and send a broadcast with all the info! ",
    "start": "2024-12-16",
    "end": "2024-12-16",
    "type": "SMS",
    "url": "",
    "color": "#4f11ee",
    "broadcastUrl": "https://www.emotiveapp.co/broadcast?&title=Holiday%20Gift%20Cards&message=~%23%7CBRAND%7C%23~%3A%20Still%20shopping%3F%20We%E2%80%99ve%20got%20you%20covered!%20%F0%9F%8E%81%20Send%20an%20e-gift%20card%2C%20and%20we%E2%80%99ll%20deliver%20it%20straight%20to%20their%20inbox.%20Instant%20delivery%2C%20no%20wrapping%20needed.%20Shop%20now%3A%20~%23%7CLINK%7C%23~%20&imageUrl=https%3A%2F%2Fimages.ctfassets.net%2Fdhi2t25jmryf%2F21euppppHZ30yTuf3ZhHUs%2F082212292f5eb629ae7716c222da230d%2FGift_Cards.gif&utm_medium=guide"
  },
  {
    "id": "1734632866304",
    "title": "New Year's Eve",
    "description": "Greet your customers and send your wishes for them this 2025. Not everything has to be a sale during moments like this, and your customers will appreciate it.",
    "start": "2024-12-31",
    "end": "2024-12-31",
    "type": "SMS",
    "url": "",
    "color": "#4c11ee",
    "broadcastUrl": "https://www.emotiveapp.co/broadcast?&title=New%20Year's%20Eve&message=~%23%7CBRAND%7C%23~%3A%205...4...3...2...1...%20Happy%20New%20Savings!%20%F0%9F%8E%8A%20Jumpstart%202024%20with%20fantastic%20deals%20up%20to%20XX%25!%20Your%20countdown%20to%20savings%20starts%20now%3A%20~%23%7CLINK%7C%23~%20&imageUrl=https%3A%2F%2Fimages.ctfassets.net%2Fdhi2t25jmryf%2F5HdAAUCOaBC6LHBpvEZLIY%2F1df6dcfc8ab0c899ec774cd6f33f017d%2FGIF_-8_New_Year_s_Day.gif&utm_medium=guide"
  },
  {
    "id": "1734633296740",
    "title": "End of Year Sale",
    "description": "Join your subscribers in closing the year on a high note with a special markdown!",
    "start": "2024-12-30",
    "end": "2024-12-30",
    "type": "SMS",
    "url": "",
    "color": "#4c11ee",
    "broadcastUrl": "https://www.emotiveapp.co/broadcast?&title=End%20of%20Year%20Sale&message=~%23%7CBRAND%7C%23~%3A%20The%20grand%20finale%20you've%20been%20waiting%20for!%20Extra%20XX%25%20off%20clearance%20to%20end%202024%20with%20a%20bang.%20Time%20to%20treat%20yourself%3A%20~%23%7CLINK%7C%23~%20&imageUrl=https%3A%2F%2Fimages.ctfassets.net%2Fdhi2t25jmryf%2F3Z3uTzjlS4qLOfnyKSeniU%2F709da829e0c196e3895ff50af30b2cfc%2FGIF_-1_New_Year-s_Sales.gif&utm_medium=guide"
  },
  {
    "id": "1734633443822",
    "title": "National Chocolate Candy Day",
    "description": "Encourage your subscribers to indulge in the nostalgic to the decadent this holiday season!",
    "start": "2024-12-28",
    "end": "2024-12-28",
    "type": "SMS",
    "url": "",
    "color": "#4c11ee",
    "broadcastUrl": "https://www.emotiveapp.co/broadcast?&title=National%20Chocolate%20Candy%20Day&message=~%23%7CBRAND%7C%23~%3A%20Life%20is%20sweeter%20with%20chocolate!%20Treat%20yourself%20to%20something%20special%20this%20National%20Chocolate%20Candy%20Day.%20Shop%20our%20delights%20up%20to%20XX%25%20off%20with%20code%20~%23%7CDISCOUNT%7C%23~%3A%20~%23%7CLINK%7C%23~%20&utm_medium=guide"
  },
  {
    "id": "1734633476300",
    "title": "National Champagne Day",
    "description": "The New Year's spirit is already catching on! Celebrate with your subscribers with a promotion on your recommended bottle.",
    "start": "2024-12-29",
    "end": "2024-12-29",
    "type": "SMS",
    "url": "",
    "color": "#4c11ee",
    "broadcastUrl": "https://www.emotiveapp.co/broadcast?&title=National%20Champagne%20Day&message=~%23%7CBRAND%7C%23~%3A%20Time%20to%20pop%20some%20bubbly!%20%F0%9F%A5%82%20National%20Champagne%20Day%20%3D%20XX%25%20off%20site-wide.%20Use%20code%20~%23%7CDISCOUNT%7C%23~%20to%20make%20today%20extra%20special.%20Cheers%20to%20savings%3A%20~%23%7CLINK%7C%23~%20&utm_medium=guide"
  },
  {
    "id": "1735851660891",
    "title": "Dry January",
    "description": "Whether your brand offers alcohol alternatives or you just want to promote a new health product this month, sharing a broadcast about Dry January is the perfect opportunity!",
    "start": "2025-01-04",
    "end": "2025-01-04",
    "type": "SMS",
    "url": "",
    "color": "#4c11ee",
    "broadcastUrl": "https://www.emotiveapp.co/broadcast?&title=Dry%20January&message=~%23%7CBRAND%7C%23~%3A%20Cheers%20to%20a%20fresh%20start%20in%202025!%20Kick%20off%20Dry%20January%20with%20~%23%7CDISCOUNT%7C%23~%25%20off%20~%23%7CPRODUCT%7C%23~!%20%F0%9F%99%8C%20Hurry%2C%20this%20offer%20ends%20~%23%7CDATE%7C%23~.%20Tap%20to%20shop%3A%20~%23%7CLINK%7C%23~%20&imageUrl=https%3A%2F%2Fimages.ctfassets.net%2Fdhi2t25jmryf%2F2Wl2Qz4nZt8ucrlXd4eGb6%2F6b47dcb40249fd076bd639487cce4374%2FGIF_-6_Dry_January.gif&utm_medium=guide"
  },
  {
    "id": "1735851708297",
    "title": "Self Love Month",
    "description": "Run a month-long promotion in honor of Self Love Month or simply send a heartfelt message to your subscribers as a reminder to take care of themselves this month and every month. \n",
    "start": "2025-01-13",
    "end": "2025-01-13",
    "type": "SMS",
    "url": "",
    "color": "#4c11ee",
    "broadcastUrl": "https://www.emotiveapp.co/broadcast?&title=Self%20Love%20Month&message=~%23%7CBRAND%7C%23~%3A%20February%20is%20all%20about%20YOU!%20%F0%9F%92%96%20Get%20~%23%7CDISCOUNT%7C%23~%25%20off%20your%20self-care%20favorites%20with%20~%23%7CCODE%7C%23~.%20Treat%20yourself%20today%3A%20%20~%23%7CLINK%7C%23~%20&imageUrl=https%3A%2F%2Fimages.ctfassets.net%2Fdhi2t25jmryf%2F2YPfiXscJ0cdWtqj3ghHQU%2F6a147e08ea236ddf1bbb18789d6cfa18%2FGIF_-5_Self-Love_Month.gif&utm_medium=guide"
  },
  {
    "id": "1735851763074",
    "title": "New Year's Day",
    "description": "New year, new broadcast, right? Share a message celebrating the day or offer a flash sale sitewide or product specific.\n",
    "start": "2025-01-01",
    "end": "2025-01-01",
    "type": "SMS",
    "url": "",
    "color": "#4c11ee",
    "broadcastUrl": "https://www.emotiveapp.co/broadcast?&title=New%20Year's%20Day&message=~%23%7CBRAND%7C%23~%3A%20Happy%20New%20Year%20from%20everyone%20at%20BRAND!%20%F0%9F%8E%89%20As%20we%20step%20into%202025%2C%20we%E2%80%99re%20filled%20with%20gratitude%20for%20your%20support.%20Here's%20to%20a%20year%20of%20new%20adventures%20together.%20Cheers%20to%20you!%20~%23%7CLINK%7C%23~%20&imageUrl=https%3A%2F%2Fimages.ctfassets.net%2Fdhi2t25jmryf%2F5HdAAUCOaBC6LHBpvEZLIY%2F1df6dcfc8ab0c899ec774cd6f33f017d%2FGIF_-8_New_Year_s_Day.gif&utm_medium=guide"
  },
  {
    "id": "1735851811197",
    "title": "Long Weekend Sale ",
    "description": "Start off the first month of 2025 strong with a weekend-long promotion. \n",
    "start": "2025-01-18",
    "end": "2025-01-20",
    "type": "SMS",
    "url": "",
    "color": "#4c11ee",
    "broadcastUrl": "https://www.emotiveapp.co/broadcast?&title=Long%20Weekend%20Sale%20&message=~%23%7CBRAND%7C%23~%3A%20%F0%9F%98%B1%20You%E2%80%99re%20invited%20to%20the%20sale%20everyone%20will%20talk%20about!%20Our%20Long%20Weekend%20bonanza%20is%20here%20with%20~%23%7CDISCOUNT%7C%23~%25%20off%20sitewide.%20Code%3A%20~%23%7CCODE%7C%23~.%20Before%20it's%20all%20gone%20by%201%2F20%2C%20shop%20here%3A%20~%23%7CLINK%7C%23~%20&imageUrl=https%3A%2F%2Fimages.ctfassets.net%2Fdhi2t25jmryf%2FB4L4hO1e6SbcBxZB2LMPZ%2F6cd44f2026f851b34fdf699716c4aa21%2FIMAGE_-14_Long_Weekend_Sale.png&utm_medium=guide"
  },
  {
    "id": "1735851847478",
    "title": "Martin Luther King Jr. Day",
    "description": "Honor the life and legacy of Dr. Martin Luther King Jr. by sharing a message of gratitude, reflecting on his impact, or providing educational resources to your subscribers.\n",
    "start": "2025-01-20",
    "end": "2025-01-20",
    "type": "SMS",
    "url": "",
    "color": "#4c11ee",
    "broadcastUrl": "https://www.emotiveapp.co/broadcast?&title=Martin%20Luther%20King%20Jr.%20Day&message=Where%20would%20we%20be%20without%20him%3F%20~%23%7CBRAND%7C%23~%20proudly%20recognizes%20the%20life%20and%20contributions%20of%20Reverend%20Dr.%20Martin%20Luther%20King%20Jr.%20Tap%20to%20learn%20more%20about%20his%20impact%3A%20~%23%7CLINK%7C%23~%20&imageUrl=https%3A%2F%2Fimages.ctfassets.net%2Fdhi2t25jmryf%2F4oNMFFWID9aKtECnSvQCct%2F1dbf3423728bb8119bf18707bd2cbd18%2FGIF_-13_MLK_Jr._Day.gif&utm_medium=guide"
  },
  {
    "id": "1735851887744",
    "title": "International Mind-Body Wellness Day",
    "description": "Kick off the new year by prioritizing self-care. Celebrate International Mind-Body Wellness Day with actionable tips or a special 24-hour sale to inspire your audience!\n",
    "start": "2025-01-03",
    "end": "2025-01-03",
    "type": "SMS",
    "url": "",
    "color": "#4c11ee",
    "broadcastUrl": "https://www.emotiveapp.co/broadcast?&title=International%20Mind-Body%20Wellness%20Day&message=Happy%20International%20Mind-Body%20Wellness%20Day!%20Take%20the%20first%20step%20toward%20your%20best%20self%20with%20help%20from%20~%23%7CBRAND%7C%23~.%20Enjoy%20~%23%7CDISCOUNT%7C%23~%25%20off%20~%23%7CPRODUCT%7C%23~%20today%20only%20with%20~%23%7CCODE%7C%23~%3A%20~%23%7CLINK%7C%23~%20&imageUrl=https%3A%2F%2Fimages.ctfassets.net%2Fdhi2t25jmryf%2F3rQxZ3tU1uvKSew4V9o02Y%2F26933d273f18258561fc9bb0340e9426%2FGIF_-9_International_Mind-Body_Wellness_Day.gif&utm_medium=guide"
  },
  {
    "id": "1735851973466",
    "title": "National Keto Day",
    "description": "Support your subscribers in reaching their health goals with a broadcast celebrating National Keto Day! Highlight how your products make sticking to a keto lifestyle easier and more enjoyable.\n",
    "start": "2025-01-05",
    "end": "2025-01-05",
    "type": "SMS",
    "url": "",
    "color": "#4c11ee",
    "broadcastUrl": "https://www.emotiveapp.co/broadcast?&title=National%20Keto%20Day&message=~%23%7CBRAND%7C%23~%3A%20Happy%20National%20Keto%20Day%2C%20~%23%7CNAME%7C%23~!%20Staying%20on%20track%20never%20tasted%20so%20good.%20Enjoy%20~%23%7CDISCOUNT%7C%23~%25%20off%20~%23%7CPRODUCT%7C%23~%20with%20~%23%7CCODE%7C%23~%20at%20checkout.%20Treat%20yourself%20and%20shop%20here%3A%20~%23%7CLINK%7C%23~%20&imageUrl=https%3A%2F%2Fimages.ctfassets.net%2Fdhi2t25jmryf%2F3Icnahml8ZB5RBwvOhutOn%2Fb1d9c045993bbda882c004ab37da425e%2FGIF_-9_National_Keto_Day.gif&utm_medium=guide"
  },
  {
    "id": "1735852005818",
    "title": "National Cuddle Up Day",
    "description": "Celebrate National Cuddle Up Day by giving your subscribers the perfect excuse to cozy up! Promote a flash sale or your latest collection to keep them warm and comfy.\n",
    "start": "2025-01-06",
    "end": "2025-01-06",
    "type": "SMS",
    "url": "",
    "color": "#4c11ee",
    "broadcastUrl": "https://www.emotiveapp.co/broadcast?&title=National%20Cuddle%20Up%20Day&message=~%23%7CBRAND%7C%23~%3A%20It%E2%80%99s%20National%20Cuddle%20Up%20Day%2C%20~%23%7CNAME%7C%23~!%20Time%20to%20get%20cozy%20and%20save%20big%20with%20our%20~%23%7CDISCOUNT%7C%23~%25%20off%20flash%20sale.%20%F0%9F%A7%B8%20Tap%20to%20shop%20and%20warm%20up%20your%20day%3A%20~%23%7CLINK%7C%23~%20&imageUrl=https%3A%2F%2Fimages.ctfassets.net%2Fdhi2t25jmryf%2F1zGDH4v6Zgq78m9REjuMn9%2F88886df1026a2916db5f9dde54999ae5%2FGIF_-10_National_Cuddle_Up_Day.gif&utm_medium=guide"
  },
  {
    "id": "1735852037126",
    "title": "National Winter Skin Relief Day",
    "description": "Help your subscribers beat the harsh effects of winter on their skin. Use National Winter Skin Relief Day to spotlight your cold-weather skincare essentials and share how they can restore that healthy glow!\n",
    "start": "2025-01-09",
    "end": "2025-01-09",
    "type": "SMS",
    "url": "",
    "color": "#4c11ee",
    "broadcastUrl": "https://www.emotiveapp.co/broadcast?&title=National%20Winter%20Skin%20Relief%20Day&message=Cold%20weather%20got%20your%20skin%20feeling%20dry%3F%20%E2%9D%84%EF%B8%8F%20We%E2%80%99ve%20got%20you%20covered!%20Enjoy%20~%23%7CDISCOUNT%7C%23~%25%20OFF%20our%20skin-saving%20~%23%7CPRODUCT%7C%23~%20with%20code%20~%23%7CCODE%7C%23~%20at%20checkout.%20Shop%20~%23%7CBRAND%7C%23~%3A%20~%23%7CLINK%7C%23~%20&imageUrl=%5Bobject%20Object%5D&utm_medium=guide"
  },
  {
    "id": "1735852069654",
    "title": "National Dress Up Your Pet Day",
    "description": "Celebrate National Dress Up Your Pet Day by encouraging your subscribers to spoil their furry friends! Promote your latest products or offer a special discount to make their pets the best-dressed in town.\n",
    "start": "2025-01-14",
    "end": "2025-01-14",
    "type": "SMS",
    "url": "",
    "color": "#4c11ee",
    "broadcastUrl": "https://www.emotiveapp.co/broadcast?&title=National%20Dress%20Up%20Your%20Pet%20Day&message=%20~%23%7CBRAND%7C%23~%3A%20Upgrade%20your%20pet%E2%80%99s%20style%20game!%20%F0%9F%90%95%20Celebrate%20National%20Dress%20Up%20Your%20Pet%20Day%20with%20~%23%7CDISCOUNT%7C%23~%25%20off%20everything%2C%20today%20only.%20No%20code%20needed%E2%80%94shop%20here%3A%20~%23%7CLINK%7C%23~%20&imageUrl=https%3A%2F%2Fimages.ctfassets.net%2Fdhi2t25jmryf%2F6wgXgoCeqHNvOIwSsm5B04%2F7d02cd30115d1c34677a9717cc59911a%2FGIF_-12_National_Dress_Up_Your_Pet_Day.gif&utm_medium=guide"
  },
  {
    "id": "1735852113682",
    "title": "National Hat Day",
    "description": "Give your subscribers a reason to shop! Offer a special promotion on your hat collection and thank them for being loyal customers.\n",
    "start": "2025-01-16",
    "end": "2025-01-16",
    "type": "SMS",
    "url": "",
    "color": "#4c11ee",
    "broadcastUrl": "https://www.emotiveapp.co/broadcast?&title=National%20Hat%20Day&message=%20~%23%7CBRAND%7C%23~%3A%20Hats%20off%20to%20you!%20%F0%9F%8E%A9%20Celebrate%20National%20Hat%20Day%20with%20~%23%7CDISCOUNT%7C%23~%25%20off%20ALL%20hats.%20Use%20code%20~%23%7CCODE%7C%23~%20at%20checkout%2C%20now%20through%20midnight%20tonight!%20Shop%20now%3A%20~%23%7CLINK%7C%23~%20&imageUrl=https%3A%2F%2Fimages.ctfassets.net%2Fdhi2t25jmryf%2F72UJcBBQFp7T6AF02EPsaZ%2Fb635828856a0e1e4a03dd8139791b1f1%2FGIF_-13_National_Hat_Day.gif&utm_medium=guide"
  },
  {
    "id": "1735852146418",
    "title": "National Get To Know Your Customer Day",
    "description": "Take this opportunity to connect with your subscribers and learn how to serve them better. Use a quick survey to gather feedback and reward their time with an exclusive discount.\n",
    "start": "2025-01-16",
    "end": "2025-01-16",
    "type": "SMS",
    "url": "",
    "color": "#4c11ee",
    "broadcastUrl": "https://www.emotiveapp.co/broadcast?&title=National%20Get%20To%20Know%20Your%20Customer%20Day&message=It%E2%80%99s%20Get%20To%20Know%20Your%20Customers%20Day%2C%20and%20we%20want%20to%20hear%20from%20YOU!%20Help%20us%20improve%20~%23%7CBRAND%7C%23~%20by%20taking%20our%20quick%20survey%20and%20get%20an%20exclusive%20discount%3A%20~%23%7CLINK%7C%23~%20&imageUrl=%5Bobject%20Object%5D&utm_medium=guide"
  },
  {
    "id": "1735852207143",
    "title": "National Use Your Gift Card Day",
    "description": "Remind your subscribers to use their holiday gift cards or run a promotion to boost new gift card sales. Remind them to shop or discover your latest offerings.\n",
    "start": "2025-01-18",
    "end": "2025-01-18",
    "type": "SMS",
    "url": "",
    "color": "#4c11ee",
    "broadcastUrl": "https://www.emotiveapp.co/broadcast?&title=National%20Use%20Your%20Gift%20Card%20Day&message=~%23%7CBRAND%7C%23~%3A%20National%20Use%20Your%20Gift%20Card%20Day%20is%20here!%20%F0%9F%9B%8D%EF%B8%8F%20Use%20your%20holiday%20Gift%20Card%20on%20our%20latest%20arrivals.%20Shop%20now%20and%20find%20something%20you%E2%80%99ll%20love%3A%20~%23%7CLINK%7C%23~%20&imageUrl=https%3A%2F%2Fimages.ctfassets.net%2Fdhi2t25jmryf%2F6Q7Q9secIXbVVXz06OCCMT%2F870711fa3af57ba50dead5dc1486fa5d%2FGIF_-15_National_Use_Your_Gift_Card_Day.gif&utm_medium=guide"
  },
  {
    "id": "1735852248487",
    "title": "National Cheese Lover's Day",
    "description": "Food brands: Celebrate National Cheese Lover's Day with an irresistible offer for your subscribers. Highlight a promotion or special deal that honors everyone’s favorite dairy delight!\n",
    "start": "2025-01-20",
    "end": "2025-01-20",
    "type": "SMS",
    "url": "",
    "color": "#4c11ee",
    "broadcastUrl": "https://www.emotiveapp.co/broadcast?&title=National%20Cheese%20Lover's%20Day&message=~%23%7CBRAND%7C%23~%3A%20Break%20out%20the%20crackers...%20it%E2%80%99s%20National%20Cheese%20Lover%E2%80%99s%20Day!%20%F0%9F%A7%80%20Enjoy%20FREE%20shipping%20on%20your%20order%20through%20~%23%7CDATE%7C%23~.%20No%20code%20needed.%20Tap%20to%20shop%3A%20~%23%7CLINK%7C%23~%20&imageUrl=%5Bobject%20Object%5D&utm_medium=guide"
  },
  {
    "id": "1735852286247",
    "title": "International Sweatpants Day",
    "description": "Celebrate the ultimate day for comfort! Use International Sweatpants Day to promote your loungewear collection or offer a special discount to keep your subscribers cozy and stylish.\n",
    "start": "2025-01-21",
    "end": "2025-01-21",
    "type": "SMS",
    "url": "",
    "color": "#4c11ee",
    "broadcastUrl": "https://www.emotiveapp.co/broadcast?&title=International%20Sweatpants%20Day&message=~%23%7CBRAND%7C%23~%3A%20Get%20cozy%20with%20us!%20%F0%9F%9B%8B%EF%B8%8F%20Celebrate%20International%20Sweatpants%20Day%20with%20~%23%7CDISCOUNT%7C%23~%25%20off%20all%20sweatpants.%20Use%20~%23%7CCODE%7C%23~%20at%20checkout%2C%20today%20only!%20Shop%20now%3A%20~%23%7CLINK%7C%23~%20&imageUrl=%5Bobject%20Object%5D&utm_medium=guide"
  },
  {
    "id": "1735852320532",
    "title": "National Compliment Day",
    "description": "Everyone loves a kind word! Use National Compliment Day to show your subscribers how much you appreciate them. Pair a heartfelt message with a flash sale to thank them for their support.\n",
    "start": "2025-01-24",
    "end": "2025-01-24",
    "type": "SMS",
    "url": "",
    "color": "#4c11ee",
    "broadcastUrl": "https://www.emotiveapp.co/broadcast?&title=National%20Compliment%20Day&message=~%23%7CBRAND%7C%23~%3A%20Hey%20~%23%7CNAME%7C%23~%2C%20we%20think%20you%E2%80%99re%20pretty%20awesome!%20%F0%9F%92%96%20Thanks%20for%20being%20part%20of%20our%20community.%20Celebrate%20National%20Compliment%20Day%20with%20a%20little%20shopping%3A%20~%23%7CLINK%7C%23~%20&imageUrl=%5Bobject%20Object%5D&utm_medium=guide"
  },
  {
    "id": "1735852356879",
    "title": "National Spouses Day",
    "description": "Show your subscribers some love for National Spouses Day by offering deals they can’t resist. Warm them up ahead of Valentine’s Day with special promotions!\n",
    "start": "2025-01-26",
    "end": "2025-01-26",
    "type": "SMS",
    "url": "",
    "color": "#4c11ee",
    "broadcastUrl": "https://www.emotiveapp.co/broadcast?&title=National%20Spouses%20Day&message=~%23%7CBRAND%7C%23~%3A%20Show%20your%20partner%20in%20crime%20some%20love!%20%F0%9F%92%95%20Today%20only%2C%20buy%20one%20~%23%7CPRODUCT%20%7C%23~and%20get%20another%20FREE.%20Use%20~%23%7CCODE%7C%23~%20at%20checkout%20to%20make%20it%20extra%20special%3A%20~%23%7CLINK%7C%23~%20&imageUrl=%5Bobject%20Object%5D&utm_medium=guide"
  },
  {
    "id": "1735852396423",
    "title": "National Green Juice Day",
    "description": "Give your subscribers a fresh reason to sip and nourish! Use National Green Juice Day to highlight your top wellness products or offer a deal on a multi-day cleanse to inspire their healthy habits.\n",
    "start": "2025-01-26",
    "end": "2025-01-26",
    "type": "SMS",
    "url": "",
    "color": "#4c11ee",
    "broadcastUrl": "https://www.emotiveapp.co/broadcast?&title=National%20Green%20Juice%20Day&message=Fresh%20start%2C%20anyone%3F%20%F0%9F%A5%AC%20It%E2%80%99s%20Green%20Juice%20Day!%20Take%20~%23%7CDISCOUNT%7C%23~%25%20off%20your%20order%20with%20~%23%7CCODE%7C%23~%2C%20now%20through%20~%23%7CDATE%7C%23~.%20Shop%20~%23%7CBRAND%7C%23~%20and%20fuel%20your%20health%3A%20~%23%7CLINK%7C%23~%20&imageUrl=%5Bobject%20Object%5D&utm_medium=guide"
  },
  {
    "id": "1735852426199",
    "title": "National Hot Chocolate Day",
    "description": "Warm up your subscribers with a sweet offer in honor of National Hot Chocolate Day. Spotlight your best-sellers or new arrivals and pair it with a cozy discount!\n",
    "start": "2025-01-31",
    "end": "2025-01-31",
    "type": "SMS",
    "url": "",
    "color": "#4c11ee",
    "broadcastUrl": "https://www.emotiveapp.co/broadcast?&title=National%20Hot%20Chocolate%20Day&message=~%23%7CBRAND%7C%23~%3A%20Happy%20National%20Hot%20Chocolate%20Day!%20Grab%20a%20mug%2C%20get%20comfy%2C%20and%20enjoy%20~%23%7CDISCOUNT%7C%23~%25%20off%20~%23%7CPRODUCT%7C%23~.%20Use%20~%23%7CCODE%20%7C%23~at%20checkout.%20Warm%20up%20here%20%3A~%23%7CLINK%7C%23~%20&imageUrl=https%3A%2F%2Fimages.ctfassets.net%2Fdhi2t25jmryf%2F5Qq98B6aVg4XJIlEL2b608%2F01ea17f2f38b3dfd172d8dc2a5f823d5%2FGIF_-19_National_Hot_Chocolate_Day.gif&utm_medium=guide"
  },
  {
    "id": "1735852494975",
    "title": "New Year's Day Offers",
    "description": "Day 1 of 365. Celebrate it with a broadcast to your subscribers offering a sitewide flash sale or a promotion on a best-selling product.\n",
    "start": "2025-01-01",
    "end": "2025-01-01",
    "type": "SMS",
    "url": "",
    "color": "#4c11ee",
    "broadcastUrl": "https://www.emotiveapp.co/broadcast?&title=New%20Year's%20Day%20Offers&message=Ready%20for%20a%20fresh%20start%3F%20%F0%9F%92%AA%20Start%20your%20new%20routine%20with%20~%23%7CBRAND%7C%23~%20and%20score%20~%23%7CDISCOUNT%7C%23~%25%20off%20your%20first%20step.%20Use%20~%23%7CCODE%7C%23~%20at%20checkout%20to%20shop%3A%20~%23%7CLINK%7C%23~%20&imageUrl=https%3A%2F%2Fimages.ctfassets.net%2Fdhi2t25jmryf%2FZB0iGhbW2MasUxf3uUlvq%2F01545b7c93ad85cf05b0cf92b7893e9a%2FGIF_-2_New_Year-s_Resolutions.gif&utm_medium=guide"
  },
  {
    "id": "1735852526566",
    "title": "New Year's Sales",
    "description": "New year, new sale! Send a broadcast to celebrate the start of the new year by showing off current promotions and sales.\n",
    "start": "2025-01-02",
    "end": "2025-01-02",
    "type": "SMS",
    "url": "",
    "color": "#4c11ee",
    "broadcastUrl": "https://www.emotiveapp.co/broadcast?&title=New%20Year's%20Sales&message=~%23%7CBRAND%7C%23~%3A%20Hit%20reset%20for%20the%20new%20year!%20Refresh%20your%202025%20with%20~%23%7CDISCOUNT%7C%23~%25%20OFF%20your%20favorites%20through%20~%23%7CDATE%7C%23~.%20Don%E2%80%99t%20miss%20out%20-%20tap%20here%3A%20~%23%7CLINK%7C%23~%20&imageUrl=https%3A%2F%2Fimages.ctfassets.net%2Fdhi2t25jmryf%2F3Z3uTzjlS4qLOfnyKSeniU%2F709da829e0c196e3895ff50af30b2cfc%2FGIF_-1_New_Year-s_Sales.gif&utm_medium=guide"
  },
  {
    "id": "1735852574102",
    "title": "New Year's Resolutions",
    "description": "New year, new YOU! Get your subscribers inspired with a heartfelt message or help them jumpstart their goals with a promotion.\n",
    "start": "2025-01-03",
    "end": "2025-01-03",
    "type": "SMS",
    "url": "",
    "color": "#4c11ee",
    "broadcastUrl": "https://www.emotiveapp.co/broadcast?&title=New%20Year's%20Resolutions&message=Hey%20~%23%7CNAME%7C%23~%2C%20cheers%20to%20a%20brand-new%20year!%20Whether%20it%E2%80%99s%20big%20plans%20or%20small%20wins%2C%20~%23%7CBRAND%7C%23~%20is%20here%20to%20keep%20you%20on%20track%20in%202025.%20Ready%20to%20crush%20it%3F%20%F0%9F%92%AA%20Let%E2%80%99s%20go%3A%20~%23%7CLINK%7C%23~%20&imageUrl=https%3A%2F%2Fimages.ctfassets.net%2Fdhi2t25jmryf%2F6Pft6ZSC8QFyHj3UHqDmja%2F176829326ca73b0e453e34a17e43af73%2FGIF_-2_New_Year_s_Resolutions.gif&utm_medium=guide"
  },
  {
    "id": "1735852612399",
    "title": "Health & Wellness - Customer Education",
    "description": "The new year is the best time for your brand to highlight ways to maintain health and wellness goals! Share healthy recipes, blog posts, and more.\n",
    "start": "2025-01-07",
    "end": "2025-01-07",
    "type": "SMS",
    "url": "",
    "color": "#4c11ee",
    "broadcastUrl": "https://www.emotiveapp.co/broadcast?&title=Health%20%26%20Wellness%20-%20Customer%20Education&message=~%23%7CBRAND%7C%23~%3A%20Healthy%20eating%3F%20Let%E2%80%99s%20take%20it%20one%20step%20(or%20bite!)%20at%20a%20time.%20%F0%9F%A5%97%20%20Our%20first%20NEW%20recipe%20is%20here%20to%20kickstart%20your%20healthy%20eating%20journey.%20See%20it%20here%3A%20~%23%7CLINK%7C%23~%20&imageUrl=https%3A%2F%2Fimages.ctfassets.net%2Fdhi2t25jmryf%2F5eJi2YTb6aMK1MIHSGvNT1%2F5a2a09dd780657b8460d748742e4b978%2FGIF_-3_Health___Wellness_-_Customer_Education.gif&utm_medium=guide"
  },
  {
    "id": "1735852636236",
    "title": "Health & Wellness - Subscription Push",
    "description": "Encourage your subscribers to stay on top of their health goals with a broadcast about your brand's subscription services. \n",
    "start": "2025-01-08",
    "end": "2025-01-08",
    "type": "SMS",
    "url": "",
    "color": "#4c11ee",
    "broadcastUrl": "https://www.emotiveapp.co/broadcast?&title=Health%20%26%20Wellness%20-%20Subscription%20Push&message=~%23%7CBRAND%7C%23~%3A%20Keep%20~%23%7CPRODUCT%7C%23~%20stocked%20and%20stress-free!%20%F0%9F%92%A1%20Subscribe%20now%20and%20save%20up%20to%20~%23%7CDISCOUNT%7C%23~%25.%20Manage%20it%20your%20way%E2%80%94pause%20or%20cancel%20anytime.%20Ready%20to%20simplify%3F%20Tap%20here%3A%20~%23%7CLINK%7C%23~%20&imageUrl=%5Bobject%20Object%5D&utm_medium=guide"
  },
  {
    "id": "1735852664870",
    "title": "National Hobby Month",
    "description": "There's no time like the start of the new year to learn something new! Celebrate National Hobby Month by sharing a spotlight on a best-selling product or run a 24-hour sale. \n",
    "start": "2025-01-10",
    "end": "2025-01-10",
    "type": "SMS",
    "url": "",
    "color": "#4c11ee",
    "broadcastUrl": "https://www.emotiveapp.co/broadcast?&title=National%20Hobby%20Month&message=~%23%7CBRAND%7C%23~%3A%20Ready%20to%20try%20something%20new%20this%20year%3F%20We%E2%80%99ve%20got%20you!%20Get%20~%23%7CDISCOUNT%7C%23~%25%20off%20your%20next%20purchase%20with%20~%23%7CCODE%7C%23~%2C%20just%20in%20time%20for%20National%20Hobby%20Month.%20Let%E2%80%99s%20make%20it%20happen%3A%20~%23%7CLINK%7C%23~%20&imageUrl=https%3A%2F%2Fimages.ctfassets.net%2Fdhi2t25jmryf%2F6f1IvLXFcy7CmMRRzQJTQN%2Fc8b5363b8cfa0aac1b516a54418bc3e1%2FGIF_-4_National_Hobby_Month.gif&utm_medium=guide"
  },
  {
    "id": "1735852803500",
    "title": "Valentine's Day 2/14 - Order Ahead",
    "description": "Don't let your subscribers procrastinate finding the perfect present ahead of Valentine's Day. Make sure you offer chances to order ahead!\n",
    "start": "2025-01-15",
    "end": "2025-01-15",
    "type": "SMS",
    "url": "",
    "color": "#4c11ee",
    "broadcastUrl": "https://www.emotiveapp.co/broadcast?&title=Valentine's%20Day%202%2F14%20-%20Order%20Ahead&message=Looking%20for%20the%20perfect%20Valentine's%20gift%3F%20It's%20waiting%20for%20you%20at%20~%23%7CBRAND%7C%23~!%20Grab%20the%20perfect%20gift%20and%20save%20~%23%7CDISCOUNT%7C%23~%25%20with%20~%23%7CCODE%7C%23~%20at%20checkout.%20Don't%20wait%E2%80%94tap%20to%20shop%3A%20%20~%23%7CLINK%7C%23~%20&imageUrl=https%3A%2F%2Fimages.ctfassets.net%2Fdhi2t25jmryf%2F56Jbo5OMHQrJQLDzQovD3X%2F6505757b29be3ab2fc662e444d4ba7e9%2FGIF_-6_Valentine-s_Day_-_Order_Ahead.gif&utm_medium=guide"
  },
  {
    "id": "1737477127978",
    "title": "National Protein Day",
    "description": "~#|BRAND|#~: Happy National Protein Day! We're celebrating with a flash sale on our best-selling powders: tap the link below to save ~#|DISCOUNT|#~% with ~#|CODE|#~ at checkout. ~#|LINK|#~",
    "start": "2025-02-27",
    "end": "2025-01-27",
    "type": "SMS",
    "url": "",
    "color": "#4c11ee",
    "broadcastUrl": "https://www.emotiveapp.co/broadcast?&title=National%20Protein%20Day&message=~%23%7CBRAND%7C%23~%3A%20Happy%20National%20Protein%20Day!%20We're%20celebrating%20with%20a%20flash%20sale%20on%20our%20best-selling%20powders%3A%20tap%20the%20link%20below%20to%20save%20~%23%7CDISCOUNT%7C%23~%25%20with%20~%23%7CCODE%7C%23~%20at%20checkout.%20~%23%7CLINK%7C%23~&utm_medium=guide"
  },
  {
    "id": "1737477271738",
    "title": "Valentine's Day - Order Ahead",
    "description": "Never underestimate the importance of reminding your subscribers to order ahead! Pro tip: offering an incentive like a limited time discount or free shipping will encourage them to move quickly.\n",
    "start": "2025-01-31",
    "end": "2025-01-31",
    "type": "SMS",
    "url": "",
    "color": "#4c11ee",
    "broadcastUrl": "https://www.emotiveapp.co/broadcast?&title=Valentine's%20Day%20-%20Order%20Ahead&message=~%23%7CBRAND%7C%23~%3A%20No%20need%20to%20rush%E2%80%94shop%20early%20and%20beat%20the%20Valentine%E2%80%99s%20Day%20crowd!%20%F0%9F%92%9D%20Order%20ahead%20and%20get%20your%20Valentine%E2%80%99s%20gift%20in%20time.%20Plus%2C%20enjoy%20free%20shipping%20on%20orders%20over%20%24__!%20Start%20shopping%20now%3A%20~%23%7CLINK%7C%23~%20&imageUrl=https%3A%2F%2Fimages.ctfassets.net%2Fdhi2t25jmryf%2F56Jbo5OMHQrJQLDzQovD3X%2F6505757b29be3ab2fc662e444d4ba7e9%2FGIF_-6_Valentine-s_Day_-_Order_Ahead.gif&utm_medium=guide"
  },
  {
    "id": "1737477448121",
    "title": "Valentine's Day - Self Care",
    "description": "Valentine's Day is the time for love in all forms! Remind your subscribers to treat themselves to something new, too. \n",
    "start": "2025-02-06",
    "end": "2025-02-06",
    "type": "SMS",
    "url": "",
    "color": "#4c11ee",
    "broadcastUrl": "https://www.emotiveapp.co/broadcast?&title=Valentine's%20Day%20-%20Self%20Care&message=~%23%7CBRAND%7C%23~%3A%20Don%E2%80%99t%20forget%20to%20spoil%20yourself%20this%20Valentine%E2%80%99s%20Day!%20%F0%9F%92%96%20%20Show%20yourself%20some%20love%20with%20~%23%7CDISCOUNT%7C%23~%20%25%20off%20and%20FREE%20shipping%20on%20orders%20over%20~%23%7CPRICE%7C%23~%20.%20Tap%20to%20shop%3A%20~%23%7CLINK%7C%23~%20&imageUrl=https%3A%2F%2Fimages.ctfassets.net%2Fdhi2t25jmryf%2F5unnH2TU7T8DeGb9K8nXz0%2Fd10bd27e65ff36ac88618a8217333c66%2FGIF_-4_Valentine-s_Day_-_Self_Care.gif&utm_medium=guide"
  },
  {
    "id": "1737477566955",
    "title": "Valentine's Day - Standard Shipping Deadline",
    "description": "Send a broadcast to your subscribers with a gentle reminder on the deadline for standard shipping. \n",
    "start": "2025-02-07",
    "end": "2025-02-07",
    "type": "SMS",
    "url": "",
    "color": "#4c11ee",
    "broadcastUrl": "https://www.emotiveapp.co/broadcast?&title=Valentine's%20Day%20-%20Standard%20Shipping%20Deadline&message=~%23%7CBRAND%7C%23~%3A%20Hey%20~%23%7CNAME%7C%23~%20!%20%E2%8F%B3Order%20now%20for%20delivery%20by%202%2F14%20with%20standard%20shipping.%20Today%E2%80%99s%20the%20final%20day%E2%80%94don%E2%80%99t%20miss%20your%20chance%20to%20grab%20the%20perfect%20gift!%20Shop%20here%3A%20~%23%7CLINK%7C%23~%20&imageUrl=https%3A%2F%2Fimages.ctfassets.net%2Fdhi2t25jmryf%2F7yfrTfoUZ2iXJOFJ9LwcOy%2F0b847e8aa516563a7a0fa8206341806e%2FGIF_-3_Valentine-s_Day_-_Shipping.gif&utm_medium=guide"
  },
  {
    "id": "1737477920481",
    "title": "Valentine's Day - 2-Day Shipping Deadline",
    "description": "Valentine's Day is right around the corner - make sure your subscribers are aware that your 2-day shipping deadline is here with a reminder to order before it's too late. \n",
    "start": "2025-02-10",
    "end": "2025-02-10",
    "type": "SMS",
    "url": "",
    "color": "#4c11ee",
    "broadcastUrl": "https://www.emotiveapp.co/broadcast?&title=Valentine's%20Day%20-%202-Day%20Shipping%20Deadline&message=~%23%7CBRAND%7C%23~%3A%20Hurry%2C%20~%23%7CNAME%7C%23~!%20%F0%9F%8F%83%E2%80%8D%E2%99%82%EF%B8%8F%20Today's%20your%20LAST%20chance%20to%20order%20with%202-day%20shipping%20and%20get%20your%20Valentine's%20Day%20gift%20in%20time.%20Don't%20miss%20out%20-%20shop%20now%3A%20~%23%7CLINK%7C%23~%20&imageUrl=https%3A%2F%2Fimages.ctfassets.net%2Fdhi2t25jmryf%2F1prgU5hwB2MnIqXLLt018j%2F50d19f91bb608ead191b09dca2bcc925%2FGIF_-1_Valentine-s_Day_2-Day_Shipping.gif&utm_medium=guide"
  },
  {
    "id": "1737478019846",
    "title": "Valentine's Day - Gift Cards",
    "description": "Don't let your subscribers show up empty-handed on the big day! Make sure you send out a broadcast promoting instant delivery gift cards. \n",
    "start": "2025-02-11",
    "end": "2025-02-11",
    "type": "Task",
    "url": "",
    "color": "#4c11ee",
    "broadcastUrl": "https://www.emotiveapp.co/broadcast?&title=Valentine's%20Day%20-%20Gift%20Cards&message=~%23%7CBRAND%7C%23~%3A%20Last-minute%20Valentine%3F%20We%E2%80%99ve%20got%20your%20back!%20Get%20an%20e-gift%20card%20delivered%20to%20their%20inbox%20in%20minutes.%20No%20shipping%20delays%2C%20just%20love!%20Shop%20now%3A%20~%23%7CLINK%7C%23~%20&imageUrl=https%3A%2F%2Fimages.ctfassets.net%2Fdhi2t25jmryf%2FoTweS5jnSGtS3TKbGGKue%2Ff99fdbe29d791604946fe09b286cb3d3%2FLAST-MINUTE_GIFTING.jpg&utm_medium=guide"
  },
  {
    "id": "1737478134550",
    "title": "Galentine's Day",
    "description": "Leslie Knope said it best - Galentine's Day is for ladies celebrating ladies! \n",
    "start": "2025-02-13",
    "end": "2025-02-13",
    "type": "SMS",
    "url": "",
    "color": "#4c11ee",
    "broadcastUrl": "https://www.emotiveapp.co/broadcast?&title=Galentine's%20Day&message=Happy%20Galentine%E2%80%99s%20Day%2C%20love!%20%F0%9F%8E%89%20Time%20to%20spoil%20your%20BFFs%20with%20a%20special%20gift%20from%20~%23%7CBRAND%7C%23~.%20Free%20shipping%20on%20orders%20over%20%24__!%20Shop%20now%3A%20~%23%7CLINK%7C%23~%20&imageUrl=https%3A%2F%2Fimages.ctfassets.net%2Fdhi2t25jmryf%2F3uQYMfku2j3dqiIq8Kd4H1%2Fb12e64a65753dcaaa030a979834ee2e9%2FGIF_-10_Galentine-s_Day.gif&utm_medium=guide"
  },
  {
    "id": "1737478358262",
    "title": "Self-Love Day",
    "description": "Turn self-care into celebration! Inspire customers to prioritize themselves with special offers that make pampering irresistible.\n",
    "start": "2025-02-13",
    "end": "2025-02-13",
    "type": "SMS",
    "url": "",
    "color": "#4c11ee",
    "broadcastUrl": "https://www.emotiveapp.co/broadcast?&title=Self-Love%20Day&message=~%23%7CBRAND%7C%23~%3A%20Today's%20all%20about%20YOU!%20Celebrate%20Self-Love%20Day%20with%20~%23%7CDISCOUNT%7C%23~%20%25%20off%20everything%20that%20makes%20you%20feel%20amazing.%20Use%20code%20~%23%7CCODE%7C%23~%20to%20treat%20yourself%3A%20~%23%7CLINK%7C%23~%20&imageUrl=https%3A%2F%2Fimages.ctfassets.net%2Fdhi2t25jmryf%2F2EEg811oyNlZMwwWdoiLpM%2Fb8b1d928a0f33960f940379c7daad89d%2FGIF_-3_Self-Love_Day.gif&utm_medium=guide"
  },
  {
    "id": "1737478455910",
    "title": "Valentine's Day",
    "description": "Build customer loyalty with genuine appreciation messages that strengthen your brand relationship.\n",
    "start": "2025-02-14",
    "end": "2025-02-14",
    "type": "SMS",
    "url": "",
    "color": "#4c11ee",
    "broadcastUrl": "https://www.emotiveapp.co/broadcast?&title=Valentine's%20Day&message=~%23%7CBRAND%7C%23~%3A%20Roses%20are%20red%2C%20violets%20are%20blue%2C%20our%20year%20is%20amazing%2C%20and%20it's%20all%20thanks%20to%20you!%20%F0%9F%92%9D%20Happy%20Valentine's%20Day%20from%20our%20family%20to%20yours!&imageUrl=https%3A%2F%2Fimages.ctfassets.net%2Fdhi2t25jmryf%2F3joddifO9XVVjpFrMtZAwt%2Ffc7e54119f206bc62c9f7646453966df%2FGIF_-4_Valentine_s_Day.gif&utm_medium=guide"
  },
  {
    "id": "1737478564420",
    "title": "Valentine's Day Sale",
    "description": "Create excitement with irresistible offers that make gift-giving (and self-gifting) even sweeter.\n",
    "start": "2025-02-14",
    "end": "2025-02-14",
    "type": "SMS",
    "url": "",
    "color": "#4c11ee",
    "broadcastUrl": "https://www.emotiveapp.co/broadcast?&title=Valentine's%20Day%20Sale&message=~%23%7CBRAND%7C%23~%3A%20Love%20is%20in%20the%20air...%20and%20so%20are%20savings!%20%F0%9F%92%98%20Get%20~%23%7CDISCOUNT%7C%23~%25%20off%20everything%20that%20makes%20your%20heart%20skip%20a%20beat.%20Fall%20in%20love%20with%20something%20new%3A%20~%23%7CLINK%7C%23~&imageUrl=https%3A%2F%2Fimages.ctfassets.net%2Fdhi2t25jmryf%2F6Jj9URaOMCYwk9mYBHHewh%2F9f0a7c0ee090df87be94face09a11190%2FGIF_-5_Valentine_s_Day_-_Sale.gif&utm_medium=guide"
  },
  {
    "id": "1737478677038",
    "title": "Singles Awareness Day",
    "description": "Celebrate independence and self-appreciation! Turn Singles Day into a festival of self-investment and personal joy.",
    "start": "2025-02-15",
    "end": "2025-02-15",
    "type": "SMS",
    "url": "",
    "color": "#4c11ee",
    "broadcastUrl": "https://www.emotiveapp.co/broadcast?&title=Singles%20Awareness%20Day&message=~%23%7CBRAND%7C%23~%3A%20Who%20needs%20a%20date%20when%20you've%20got%20great%20taste%3F%20%F0%9F%92%85%20Treat%20yourself%20to%20~%23%7CDISCOUNT%7C%23~%25%20off%20with%20code%20~%23%7CCODE%7C%23~.%20Because%20you're%20a%20whole%20vibe%20on%20your%20own%3A%20~%23%7CLINK%7C%23~&imageUrl=https%3A%2F%2Fimages.ctfassets.net%2Fdhi2t25jmryf%2F4ZWgOTmK4MhKy2n9gJXCzQ%2F79c8c16b5bafbf5e14f2ce3cdbd17473%2FGIF_-12_Singles_Awareness_Day.gif&utm_medium=guide"
  },
  {
    "id": "1737478777601",
    "title": "Random Acts of Kindness Day ",
    "description": "Spread joy and inspire generosity with offers that encourage both self-care and sharing.\n",
    "start": "2025-02-17",
    "end": "2025-02-17",
    "type": "SMS",
    "url": "",
    "color": "#4c11ee",
    "broadcastUrl": "https://www.emotiveapp.co/broadcast?&title=Random%20Acts%20of%20Kindness%20Day%20&message=~%23%7CBRAND%7C%23~%3A%20Here's%20your%20sign%20to%20spread%20some%20joy!%20~%23%7CDISCOUNT%7C%23~%25%20off%20everything%20-%20treat%20yourself%20or%20surprise%20someone%20special.%20Use%20code%20~%23%7CCODE%7C%23~%20to%20share%20the%20love%3A%20~%23%7CLINK%7C%23~&imageUrl=https%3A%2F%2Fimages.ctfassets.net%2Fdhi2t25jmryf%2F5fROPZtmnuBLiifUz3rQsi%2F8fb30c8e0cd199ffa2925ad38fc581e2%2FGIF_-13_National_Random_Acts_of_Kindness_Day.gif&utm_medium=guide"
  },
  {
    "id": "1737478946225",
    "title": "Love Your Pets Day",
    "description": "Celebrate furry family members with playful messaging that resonates with pet parents.\n",
    "start": "2025-02-20",
    "end": "2025-02-20",
    "type": "SMS",
    "url": "",
    "color": "#4c11ee",
    "broadcastUrl": "https://www.emotiveapp.co/broadcast?&title=Love%20Your%20Pets%20Day&message=~%23%7CBRAND%7C%23~%3A%20Your%20fur%20baby's%20favorite%20holiday%20is%20here!%20%F0%9F%90%BE%20Spoil%20them%20with%20~%23%7CDISCOUNT%7C%23~%25%20off%20their%20wish%20list%20using%20code%20~%23%7CCODE%7C%23~.%20Time%20to%20earn%20those%20tail%20wags%3A%20~%23%7CLINK%7C%23~&imageUrl=https%3A%2F%2Fimages.ctfassets.net%2Fdhi2t25jmryf%2F1HSHdeXlxb5wO9kH7I0mbX%2Fc4b8189b767618cd5c6abf9e861cf46b%2FGIF_-5_Valentine-s_Day_-_Pets.gif&utm_medium=guide"
  },
  {
    "id": "1737482815434",
    "title": "Lunar New year",
    "description": "Lunar New Year",
    "start": "2025-01-28",
    "end": "2025-01-28",
    "type": "SMS",
    "url": "",
    "color": "#4c11ee",
    "broadcastUrl": "https://www.emotiveapp.co/broadcast?&title=Lunar%20New%20Year&message=~%23%7CBRAND%7C%23~%3A%20The%20Wood%20Snake%E2%80%99s%20new%20year%20gift%3F%20~%23%7CDISCOUNT%7C%23~%25%20OFF%20just%20for%20you!%20%F0%9F%90%8D%20%20Use%20~%23%7CCODE%7C%23~%20at%20checkout%20and%20treat%20yourself%20to%20something%20special.%20Shop%20the%20deals%20here%3A%20~%23%7CLINK%7C%23~&imageUrl=https%3A%2F%2Fimages.ctfassets.net%2Fdhi2t25jmryf%2F1N41PstoaFIeg3llyYLDku%2F600e0383c0e416094337f868c2ab0b7f%2FGIF_-16_Lunar_New_Year.gif&utm_medium=guide"
  },
  {
    "id": "1737483043771",
    "title": "Super Bowl Order Ahead",
    "description": "Super Bowl Order Ahead",
    "start": "2025-02-02",
    "end": "2025-02-02",
    "type": "SMS",
    "url": "",
    "color": "#4c11ee",
    "broadcastUrl": "https://www.emotiveapp.co/broadcast?&title=Super%20Bowl%20Order%20Ahead&message=Hey!%20Ready%20for%20football%20season%3F%20%F0%9F%8F%88%20Grab%20~%23%7CDISCOUNT%7C%23~%25%20off%20~%23%7CPRODUCT%7C%23~%20and%20make%20your%20football%20Sundays%20even%20better.%20Just%20use%20~%23%7CCODE%7C%23~%20at%20checkout.%20Shop%20~%23%7CBRAND%7C%23~%3A%20~%23%7CLINK%7C%23~%0A&utm_medium=guide"
  },
  {
    "id": "1737483136572",
    "title": "Super Bowl Shipping Deadline",
    "description": "Super Bowl Shipping Deadline",
    "start": "2025-02-04",
    "end": "2025-02-04",
    "type": "SMS",
    "url": "",
    "color": "#4c11ee",
    "broadcastUrl": "https://www.emotiveapp.co/broadcast?&title=Super%20Bowl%20Shipping%20Deadline&message=Get%20your%20game%20face%20on!%20Ensure%20your%20~%23%7CBRAND%7C%23~%20gear%20makes%20the%20lineup%20in%20time%20for%20Super%20Bowl.%20Order%20by%20~%23%7CDATE%7C%23~%20for%20a%20touchdown-worthy%20delivery.%20Go%20long%20and%20shop%20now%3A%20~%23%7CLINK%7C%23~%0A%0A&utm_medium=guide"
  },
{
    "id": "1737655810676",
    "title": "Groundhog Day",
    "description": "Groundhog Day",
    "start": "2025-02-02",
    "end": "2025-02-02",
    "type": "SMS",
    "url": "",
    "color": "#4c11ee",
    "broadcastUrl": "https://www.emotiveapp.co/broadcast?&title=Groundhog%20Day&message=Shadow%20or%20sunshine%2C%20Groundhog%20Day%20is%20here!%20Phil%E2%80%99s%20shadow%20drama%20isn%E2%80%99t%20the%20only%20excitement%20today%E2%80%94you%E2%80%99ve%20got%20~%23%7CDISCOUNT%7C%23~%25%20off%20waiting.%20Celebrate%20today%20by%20using%20~%23%7CCODE%7C%23~%20at%20checkout.%20But%20hurry%2C%20it%E2%80%99s%20only%20good%20for%2024%20hours.%20~%23%7CLINK%7C%23~%0A%0A&utm_medium=guide"
  },
  {
    "id": "1737655925009",
    "title": "National Pizza Day",
    "description": "National Pizza Day",
    "start": "2025-02-10",
    "end": "2025-02-10",
    "type": "SMS",
    "url": "",
    "color": "#4c11ee",
    "broadcastUrl": "https://www.emotiveapp.co/broadcast?&title=National%20Pizza%20Day&message=~%23%7CBRAND%7C%23~%3A%20Who%20says%20Pizza%20Day%20isn%E2%80%99t%20every%20day%3F%20%F0%9F%8D%95%20Make%20it%20epic%20with%20our%20go-to%20homemade%20pizza%20recipe.%20It%E2%80%99s%20easy%2C%20delicious%2C%20and%20waiting%20for%20you%20right%20here%3A%20~%23%7CLINK%7C%23~%0A%0A&imageUrl=https%3A%2F%2Fimages.ctfassets.net%2Fdhi2t25jmryf%2F1FaimEB3ob3EMk1e1oZTk0%2F067ac3d8bd86df21a2962081d95363ef%2FGIF_-8_National_Pizza_Day.gif&utm_medium=guide"
  },
  {
    "id": "1737656063258",
    "title": "National Lash Day",
    "description": "National Lash Day",
    "start": "2025-02-19",
    "end": "2025-02-19",
    "type": "SMS",
    "url": "",
    "color": "#4c11ee",
    "broadcastUrl": "https://www.emotiveapp.co/broadcast?&title=National%20Lash%20Day&message=~%23%7CBRAND%7C%23~%3A%20Happy%20National%20Lash%20Day%2C%20beauty!%20Celebrate%20with%20~%23%7CDISCOUNT%7C%23~%25%20off%20sitewide%20using%20CODE%20at%20checkout.%20Tap%20to%20shop%3A%20~%23%7CLINK%7C%23~&utm_medium=guide"
  },
  {
    "id": "1737656146302",
    "title": "National Margarita Day",
    "description": "National Margarita Day",
    "start": "2025-02-22",
    "end": "2025-02-22",
    "type": "Task",
    "url": "",
    "color": "#4c11ee",
    "broadcastUrl": "https://www.emotiveapp.co/broadcast?&title=National%20Margarita%20Day&message=~%23%7CBRAND%7C%23~%3A%20Taco%20Tuesday%2C%20meet%20National%20Margarita%20Day.%20Tap%20to%20get%20our%20all-time%20favorite%20margarita%20recipe%20-%20you%20won't%20regret%20it!%20~%23%7CLINK%7C%23~&utm_medium=guide"
  },
  {
    "id": "1737657451074",
    "title": "Presidents' Day - VIP Early Access",
    "description": "Presidents' Day - VIP Early Access\n",
    "start": "2025-02-16",
    "end": "2025-01-16",
    "type": "SMS",
    "url": "",
    "color": "#4c11ee",
    "broadcastUrl": "https://www.emotiveapp.co/broadcast?&title=Presidents'%20Day%20-%20VIP%20Early%20Access&message=~%23%7CBRAND%7C%23~%3A%20Hey%20VIP!%20You're%20FIRST%20in%20line%20to%20shop%20our%20Presidents'%20Day%20Sale.%20Enjoy%20~%23%7CDISCOUNT%7C%23~%25%20sitewide%20with%20~%23%7CCODE%7C%23~%20at%20checkout!%20Shop%20now%3A%20~%23%7CLINK%7C%23~%0A&utm_medium=guide"
  },
  {
    "id": "1737657522778",
    "title": "Presidents' Day - Sale Announcement",
    "description": "Presidents' Day - Sale Announcement\n",
    "start": "2025-02-16",
    "end": "2025-02-16",
    "type": "Task",
    "url": "",
    "color": "#4c11ee",
    "broadcastUrl": "https://www.emotiveapp.co/broadcast?&title=Presidents'%20Day%20-%20Sale%20Announcement&message=~%23%7CBRAND%7C%23~%3A%20Our%20Presidents'%20Day%20sale%20starts%20now!%20Enjoy%20~%23%7CDISCOUNT%7C%23~%25%20off%20sitewide%20with%20~%23%7CCODE%7C%23~%20at%20checkout.%20Sale%20ends%202%2F20%2C%20so%20hurry!%20Tap%20to%20shop%3A%20~%23%7CLINK%7C%23~&utm_medium=guide"
  },
  {
    "id": "1737657586712",
    "title": "Presidents' Day Sale - Last Call",
    "description": "Presidents' Day Sale - Last Call",
    "start": "2025-02-18",
    "end": "2025-02-18",
    "type": "SMS",
    "url": "",
    "color": "#4c11ee",
    "broadcastUrl": "https://www.emotiveapp.co/broadcast?&title=Presidents'%20Day%20Sale%20-%20Last%20Call&message=LAST%20CHANCE%20%E2%9A%A1Our%20President's%20Day%20savings%20disappear%20at%20midnight%20tonight!%20Don't%20miss%20out%20-%20Shop%20now%3A%20~%23%7CLINK%7C%23~&utm_medium=guide"
  },
  {
    "id": "1737657700565",
    "title": "Presidents' Day Sale Extension",
    "description": "Presidents' Day Sale Extension\n",
    "start": "2025-02-19",
    "end": "2025-02-19",
    "type": "SMS",
    "url": "",
    "color": "#4c11ee",
    "broadcastUrl": "https://www.emotiveapp.co/broadcast?&title=Presidents'%20Day%20Sale%20Extension&message=SURPRISE!%20We've%20extended%20our%20Presidents'%20Day%20sale%20just%20for%20VIP%20text%20subscribers.%20Use%20~%23%7CCODE%7C%23~%20for%20~%23%7CDISCOUNT%7C%23~%25%20off%2C%20today%20only!%20~%23%7CLINK%7C%23~&utm_medium=guide"
  },
  {
    "id": "1737657828248",
    "title": "Super Bowl - Order Ahead",
    "description": "Super Bowl - Order Ahead",
    "start": "2025-01-27",
    "end": "2025-01-27",
    "type": "SMS",
    "url": "",
    "color": "#4c11ee",
    "broadcastUrl": "https://www.emotiveapp.co/broadcast?&title=Super%20Bowl%20-%20Order%20Ahead&message=Hey!%20Ready%20for%20football%20season%3F%20%F0%9F%8F%88%20Grab%20~%23%7CDISCOUNT%7C%23~%25%20off%20PRODUCT%20and%20make%20your%20football%20Sundays%20even%20better.%20Just%20use%20~%23%7CCODE%7C%23~%20at%20checkout.%20Shop%20~%23%7CBRAND%7C%23~%3A%20~%23%7CLINK%7C%23~&utm_medium=guide"
  },
  {
    "id": "1737657881269",
    "title": "Super Bowl - Shipping Deadline",
    "description": "Super Bowl - Shipping Deadline\n",
    "start": "2025-01-30",
    "end": "2025-01-30",
    "type": "SMS",
    "url": "",
    "color": "#4c11ee",
    "broadcastUrl": "https://www.emotiveapp.co/broadcast?&title=Super%20Bowl%20-%20Shipping%20Deadline&message=Get%20your%20game%20face%20on!%20Ensure%20your%20~%23%7CBRAND%7C%23~%20gear%20makes%20the%20lineup%20in%20time%20for%20Super%20Bowl.%20Order%20by%20~%23%7CDATE%7C%23~%20for%20a%20touchdown-worthy%20delivery.%20Go%20long%20and%20shop%20now%3A%20~%23%7CLINK%7C%23~%0A&utm_medium=guide"
  },
  {
    "id": "1737657958121",
    "title": "The Big Game",
    "description": "The Big Game\n",
    "start": "2025-02-09",
    "end": "2025-02-09",
    "type": "SMS",
    "url": "",
    "color": "#4c11ee",
    "broadcastUrl": "https://www.emotiveapp.co/broadcast?&title=The%20Big%20Game&message=Game%20Day%20is%20here!%20%F0%9F%8F%88%20Got%20the%20snacks%3F%20%20Get%20~%23%7CDISCOUNT%7C%23~%25%20OFF%20sitewide%20at%20BRAND%20and%20make%20it%20even%20better!%20Use%20~%23%7CCODE%7C%23~%20at%20checkout%20before%20midnight%20~%23%7CDATE%7C%23~%20and%20score%20big.%20Shop%20here%3A%20~%23%7CLINK%7C%23~%0A&utm_medium=guide"
  }
]
